[
  {
    "id": "asia-sv7a-001",
    "set_id": "asia-sv7a",
    "number": "001",
    "category": "pokemon",
    "name": {
      "ja": "タマタマ"
    },
    "pokemon": [
      "0102"
    ],
    "illustrator": "Tetsu Kayama",
    "rarity": "common",
    "regulation_mark": "H",
    "variants": [
      {
        "id": "normal",
        "images": {
          "ja": "/images/cards/asia-sv7a/ja/001.webp"
        }
      }
    ],
    "hp": 30,
    "types": [
      "grass"
    ],
    "stage": "basic",
    "attacks": [
      {
        "name": {
          "ja": "そうじゅくしんか"
        },
        "cost": [
          "normal"
        ],
        "damage": "",
        "text": {
          "ja": "このワザは、先攻プレイヤーの最初の番でも使える。このポケモンから進化するカードを、自分の山札から1枚選び、このポケモンにのせて進化させる。そして山札を切る。"
        }
      }
    ],
    "weaknesses": [
      {
        "type": "fire",
        "value": "x2"
      }
    ],
    "retreat_cost": 1,
    "flavor_text": {
      "ja": "タマタマだけに 伝わる テレパシーを 出し合っているので どんなときでも ６匹 集まれる。"
    }
  },
  {
    "id": "asia-sv7a-002",
    "set_id": "asia-sv7a",
    "number": "002",
    "category": "pokemon",
    "name": {
      "ja": "ネマシュ"
    },
    "pokemon": [
      "0755"
    ],
    "illustrator": "Tomokazu Komiya",
    "rarity": "common",
    "regulation_mark": "H",
    "variants": [
      {
        "id": "normal",
        "images": {
          "ja": "/images/cards/asia-sv7a/ja/002.webp"
        }
      }
    ],
    "hp": 60,
    "types": [
      "grass"
    ],
    "stage": "basic",
    "attacks": [
      {
        "name": {
          "ja": "くっつく"
        },
        "cost": [
          "normal"
        ],
        "damage": "10",
        "text": {}
      }
    ],
    "weaknesses": [
      {
        "type": "fire",
        "value": "x2"
      }
    ],
    "retreat_cost": 1,
    "flavor_text": {
      "ja": "頭の 傘は とても 美味しい。 森の ポケモンたちに 食べられるが 一晩で 再生する。"
    }
  },
  {
    "id": "asia-sv7a-003",
    "set_id": "asia-sv7a",
    "number": "003",
    "category": "pokemon",
    "name": {
      "ja": "マシェード"
    },
    "pokemon": [
      "0756"
    ],
    "illustrator": "Aya Kusube",
    "rarity": "uncommon",
    "regulation_mark": "H",
    "variants": [
      {
        "id": "normal",
        "images": {
          "ja": "/images/cards/asia-sv7a/ja/003.webp"
        }
      }
    ],
    "hp": 110,
    "types": [
      "grass"
    ],
    "stage": "stage1",
    "attacks": [
      {
        "name": {
          "ja": "スパイラルラッシュ"
        },
        "cost": [
          "grass",
          "normal"
        ],
        "damage": "60＋",
        "text": {
          "ja": "ウラが出るまでコインを投げ、オモテの数×30ダメージ追加。"
        }
      }
    ],
    "weaknesses": [
      {
        "type": "fire",
        "value": "x2"
      }
    ],
    "retreat_cost": 2,
    "flavor_text": {
      "ja": "点滅する 胞子の 光りで 獲物を おびき寄せて 眠らせる。 指先から 生気を 吸い取る。"
    }
  },
  {
    "id": "asia-sv7a-004",
    "set_id": "asia-sv7a",
    "number": "004",
    "category": "pokemon",
    "name": {
      "ja": "ダダリン"
    },
    "pokemon": [
      "0781"
    ],
    "illustrator": "Mori Yuu",
    "rarity": "common",
    "regulation_mark": "H",
    "variants": [
      {
        "id": "normal",
        "images": {
          "ja": "/images/cards/asia-sv7a/ja/004.webp"
        }
      }
    ],
    "hp": 130,
    "types": [
      "grass"
    ],
    "stage": "basic",
    "attacks": [
      {
        "name": {
          "ja": "レスキューアンカー"
        },
        "cost": [
          "normal"
        ],
        "damage": "",
        "text": {
          "ja": "自分のトラッシュからポケモンを2枚まで選び、相手に見せて、手札に加える。"
        }
      },
      {
        "name": {
          "ja": "はかいのイカリ"
        },
        "cost": [
          "grass",
          "normal",
          "normal"
        ],
        "damage": "80",
        "text": {
          "ja": "ダメージを与える前に、相手のバトルポケモンについている「ポケモンのどうぐ」をトラッシュする。"
        }
      }
    ],
    "weaknesses": [
      {
        "type": "fire",
        "value": "x2"
      }
    ],
    "retreat_cost": 3,
    "flavor_text": {
      "ja": "海底を 漂う 藻屑が 沈没船の 部品を 取りこんで ゴーストポケモンに 生まれ変わった。"
    }
  },
  {
    "id": "asia-sv7a-005",
    "set_id": "asia-sv7a",
    "number": "005",
    "category": "pokemon",
    "name": {
      "ja": "ザルード"
    },
    "pokemon": [
      "0893"
    ],
    "illustrator": "GOSSAN",
    "rarity": "rare",
    "regulation_mark": "H",
    "variants": [
      {
        "id": "normal",
        "images": {
          "ja": "/images/cards/asia-sv7a/ja/005.webp"
        }
      }
    ],
    "hp": 120,
    "types": [
      "grass"
    ],
    "stage": "basic",
    "attacks": [
      {
        "name": {
          "ja": "リーフドレイン"
        },
        "cost": [
          "grass"
        ],
        "damage": "20",
        "text": {
          "ja": "このポケモンのHPを「20」回復する。"
        }
      },
      {
        "name": {
          "ja": "ジャングルウィップ"
        },
        "cost": [
          "grass",
          "grass",
          "normal"
        ],
        "damage": "80＋",
        "text": {
          "ja": "のぞむなら、このポケモンについているエネルギーをすべて手札にもどし、80ダメージ追加。"
        }
      }
    ],
    "weaknesses": [
      {
        "type": "fire",
        "value": "x2"
      }
    ],
    "retreat_cost": 1,
    "flavor_text": {
      "ja": "群れを つくり 密林で 暮らす。 とても 攻撃的で 森にすむ ポケモンたちから 恐れられている。"
    }
  },
  {
    "id": "asia-sv7a-006",
    "set_id": "asia-sv7a",
    "number": "006",
    "category": "pokemon",
    "name": {
      "ja": "ポワルン たいようのすがた"
    },
    "pokemon": [
      "0351"
    ],
    "illustrator": "osare",
    "rarity": "common",
    "regulation_mark": "H",
    "variants": [
      {
        "id": "normal",
        "images": {
          "ja": "/images/cards/asia-sv7a/ja/006.webp"
        }
      }
    ],
    "hp": 70,
    "types": [
      "fire"
    ],
    "stage": "basic",
    "attacks": [
      {
        "name": {
          "ja": "こがす"
        },
        "cost": [
          "fire"
        ],
        "damage": "",
        "text": {
          "ja": "相手のバトルポケモンをやけどにする。"
        }
      },
      {
        "name": {
          "ja": "サニーアシスト"
        },
        "cost": [
          "fire",
          "normal"
        ],
        "damage": "50",
        "text": {
          "ja": "このポケモンについているエネルギーをすべて、ベンチポケモン1匹につけ替える。"
        }
      }
    ],
    "weaknesses": [
      {
        "type": "water",
        "value": "x2"
      }
    ],
    "retreat_cost": 0,
    "flavor_text": {
      "ja": "晴れた 日の ポワルンの 姿。 ヒーターの前に 置く 実験では この 形に 変化しなかった。"
    }
  },
  {
    "id": "asia-sv7a-007",
    "set_id": "asia-sv7a",
    "number": "007",
    "category": "pokemon",
    "name": {
      "ja": "バオップ"
    },
    "pokemon": [
      "0513"
    ],
    "illustrator": "Wintr Wandr",
    "rarity": "common",
    "regulation_mark": "H",
    "variants": [
      {
        "id": "normal",
        "images": {
          "ja": "/images/cards/asia-sv7a/ja/007.webp"
        }
      }
    ],
    "hp": 60,
    "types": [
      "fire"
    ],
    "stage": "basic",
    "attacks": [
      {
        "name": {
          "ja": "かえん"
        },
        "cost": [
          "fire"
        ],
        "damage": "20",
        "text": {}
      }
    ],
    "weaknesses": [
      {
        "type": "water",
        "value": "x2"
      }
    ],
    "retreat_cost": 1,
    "flavor_text": {
      "ja": "知能が 高く 木の実は 焼いてから 食べる 習性。 人の 手伝いを 好んでいる。"
    }
  },
  {
    "id": "asia-sv7a-008",
    "set_id": "asia-sv7a",
    "number": "008",
    "category": "pokemon",
    "name": {
      "ja": "バオッキー"
    },
    "pokemon": [
      "0514"
    ],
    "illustrator": "Taiga Kasai",
    "rarity": "common",
    "regulation_mark": "H",
    "variants": [
      {
        "id": "normal",
        "images": {
          "ja": "/images/cards/asia-sv7a/ja/008.webp"
        }
      }
    ],
    "hp": 90,
    "types": [
      "fire"
    ],
    "stage": "stage1",
    "attacks": [
      {
        "name": {
          "ja": "ダブルスマッシュ"
        },
        "cost": [
          "fire"
        ],
        "damage": "70×",
        "text": {
          "ja": "コインを2回投げ、オモテの数×70ダメージ。"
        }
      }
    ],
    "weaknesses": [
      {
        "type": "water",
        "value": "x2"
      }
    ],
    "retreat_cost": 1,
    "flavor_text": {
      "ja": "体の 中の 炎を 燃やして 頭や 尻尾から 火の粉を まき散らせて 敵を 焦がす。"
    }
  },
  {
    "id": "asia-sv7a-009",
    "set_id": "asia-sv7a",
    "number": "009",
    "category": "pokemon",
    "name": {
      "ja": "ウガツホムラ"
    },
    "pokemon": [
      "1020"
    ],
    "illustrator": "AKIRA EGAWA",
    "rarity": "rare",
    "regulation_mark": "H",
    "variants": [
      {
        "id": "normal",
        "images": {
          "ja": "/images/cards/asia-sv7a/ja/009.webp"
        }
      }
    ],
    "hp": 130,
    "types": [
      "fire"
    ],
    "stage": "basic",
    "attacks": [
      {
        "name": {
          "ja": "つきたおし"
        },
        "cost": [
          "fire"
        ],
        "damage": "30",
        "text": {}
      },
      {
        "name": {
          "ja": "えんじょうとつげき"
        },
        "cost": [
          "fire",
          "fire",
          "normal"
        ],
        "damage": "100＋",
        "text": {
          "ja": "相手のサイドの残り枚数が4枚以下なら、70ダメージ追加。"
        }
      }
    ],
    "weaknesses": [
      {
        "type": "water",
        "value": "x2"
      }
    ],
    "retreat_cost": 2,
    "flavor_text": {
      "ja": "目撃報告は ごくわずか。 火柱を 噴き 暴れる 姿の 短い 映像が 存在する。"
    }
  },
  {
    "id": "asia-sv7a-010",
    "set_id": "asia-sv7a",
    "number": "010",
    "category": "pokemon",
    "name": {
      "ja": "フリージオ"
    },
    "pokemon": [
      "0615"
    ],
    "illustrator": "sui",
    "rarity": "common",
    "regulation_mark": "H",
    "variants": [
      {
        "id": "normal",
        "images": {
          "ja": "/images/cards/asia-sv7a/ja/010.webp"
        }
      }
    ],
    "hp": 90,
    "types": [
      "water"
    ],
    "stage": "basic",
    "attacks": [
      {
        "name": {
          "ja": "コールサイン"
        },
        "cost": [
          "water"
        ],
        "damage": "",
        "text": {
          "ja": "自分の山札からポケモンを1枚選び、相手に見せて、手札に加える。そして山札を切る。"
        }
      },
      {
        "name": {
          "ja": "れいとうビーム"
        },
        "cost": [
          "water"
        ],
        "damage": "30",
        "text": {
          "ja": "コインを1回投げオモテなら、相手のバトルポケモンをマヒにする。"
        }
      }
    ],
    "weaknesses": [
      {
        "type": "metal",
        "value": "x2"
      }
    ],
    "retreat_cost": 1,
    "flavor_text": {
      "ja": "氷で できた 鎖を 使い 相手を 締め上げると そのまま 一気に 凍らせてしまうのだ。"
    }
  },
  {
    "id": "asia-sv7a-011",
    "set_id": "asia-sv7a",
    "number": "011",
    "category": "pokemon",
    "name": {
      "ja": "ブラックキュレムex"
    },
    "pokemon": [
      "0646"
    ],
    "illustrator": "kawayoo",
    "rarity": "double_rare",
    "regulation_mark": "H",
    "variants": [
      {
        "id": "normal",
        "images": {
          "ja": "/images/cards/asia-sv7a/ja/011.webp"
        }
      }
    ],
    "hp": 230,
    "types": [
      "water"
    ],
    "stage": "basic",
    "rule_box": "EX",
    "attacks": [
      {
        "name": {
          "ja": "アイスエイジ"
        },
        "cost": [
          "normal",
          "normal",
          "normal"
        ],
        "damage": "90",
        "text": {
          "ja": "相手のバトルポケモンがポケモンなら、そのポケモンをマヒにする。"
        }
      },
      {
        "name": {
          "ja": "ブラックフロスト"
        },
        "cost": [
          "water",
          "water",
          "normal",
          "normal"
        ],
        "damage": "250",
        "text": {
          "ja": "このポケモンにも30ダメージ。"
        }
      }
    ],
    "weaknesses": [
      {
        "type": "metal",
        "value": "x2"
      }
    ],
    "retreat_cost": 3
  },
  {
    "id": "asia-sv7a-012",
    "set_id": "asia-sv7a",
    "number": "012",
    "category": "pokemon",
    "name": {
      "ja": "ハギギシリ"
    },
    "pokemon": [
      "0779"
    ],
    "illustrator": "Shibuzoh.",
    "rarity": "uncommon",
    "regulation_mark": "H",
    "variants": [
      {
        "id": "normal",
        "images": {
          "ja": "/images/cards/asia-sv7a/ja/012.webp"
        }
      }
    ],
    "hp": 110,
    "types": [
      "water"
    ],
    "stage": "basic",
    "attacks": [
      {
        "name": {
          "ja": "かじりつく"
        },
        "cost": [
          "water",
          "normal"
        ],
        "damage": "50",
        "text": {
          "ja": "次の相手の番、このワザを受けたポケモンは、にげられない。"
        }
      }
    ],
    "weaknesses": [
      {
        "type": "lightning",
        "value": "x2"
      }
    ],
    "retreat_cost": 1,
    "flavor_text": {
      "ja": "歯ぎしりで 起こる 波紋に 陽の光が 反射するとき まわりの 水は 眩いばかりに きらめく。"
    }
  },
  {
    "id": "asia-sv7a-013",
    "set_id": "asia-sv7a",
    "number": "013",
    "category": "pokemon",
    "name": {
      "ja": "クワッス"
    },
    "pokemon": [
      "0912"
    ],
    "illustrator": "Saboteri",
    "rarity": "common",
    "regulation_mark": "H",
    "variants": [
      {
        "id": "normal",
        "images": {
          "ja": "/images/cards/asia-sv7a/ja/013.webp"
        }
      }
    ],
    "hp": 60,
    "types": [
      "water"
    ],
    "stage": "basic",
    "attacks": [
      {
        "name": {
          "ja": "つばめがえし"
        },
        "cost": [
          "water"
        ],
        "damage": "10＋",
        "text": {
          "ja": "コインを1回投げオモテなら、20ダメージ追加。"
        }
      }
    ],
    "weaknesses": [
      {
        "type": "lightning",
        "value": "x2"
      }
    ],
    "retreat_cost": 1,
    "flavor_text": {
      "ja": "流れが 急な 川も 自由に 泳ぎまわる 脚力を 持つ。 きれい好きで 思い込みが 強い。"
    }
  },
  {
    "id": "asia-sv7a-014",
    "set_id": "asia-sv7a",
    "number": "014",
    "category": "pokemon",
    "name": {
      "ja": "ウェルカモ"
    },
    "pokemon": [
      "0913"
    ],
    "illustrator": "OKACHEKE",
    "rarity": "common",
    "regulation_mark": "H",
    "variants": [
      {
        "id": "normal",
        "images": {
          "ja": "/images/cards/asia-sv7a/ja/014.webp"
        }
      }
    ],
    "hp": 100,
    "types": [
      "water"
    ],
    "stage": "stage1",
    "attacks": [
      {
        "name": {
          "ja": "アクアエッジ"
        },
        "cost": [
          "water"
        ],
        "damage": "40",
        "text": {}
      }
    ],
    "weaknesses": [
      {
        "type": "lightning",
        "value": "x2"
      }
    ],
    "retreat_cost": 1,
    "flavor_text": {
      "ja": "様々な 地方の ポケモンや 人の 動きを 見て 自らの 踊りに 取り入れる 努力家。"
    }
  },
  {
    "id": "asia-sv7a-015",
    "set_id": "asia-sv7a",
    "number": "015",
    "category": "pokemon",
    "name": {
      "ja": "ウェーニバル"
    },
    "pokemon": [
      "0914"
    ],
    "illustrator": "nagimiso",
    "rarity": "uncommon",
    "regulation_mark": "H",
    "variants": [
      {
        "id": "normal",
        "images": {
          "ja": "/images/cards/asia-sv7a/ja/015.webp"
        }
      }
    ],
    "hp": 170,
    "types": [
      "water"
    ],
    "stage": "stage2",
    "attacks": [
      {
        "name": {
          "ja": "ハイドロスプラッシュ"
        },
        "cost": [
          "water",
          "normal"
        ],
        "damage": "120",
        "text": {}
      }
    ],
    "weaknesses": [
      {
        "type": "lightning",
        "value": "x2"
      }
    ],
    "retreat_cost": 2,
    "flavor_text": {
      "ja": "異国情緒 溢れる ダンスで 見るものを 魅了し 水でできた 飾り羽根を 振りまわし 切り裂く。"
    }
  },
  {
    "id": "asia-sv7a-016",
    "set_id": "asia-sv7a",
    "number": "016",
    "category": "pokemon",
    "name": {
      "ja": "アルクジラ"
    },
    "pokemon": [
      "0974"
    ],
    "illustrator": "Ayako Ozaki",
    "rarity": "common",
    "regulation_mark": "H",
    "variants": [
      {
        "id": "normal",
        "images": {
          "ja": "/images/cards/asia-sv7a/ja/016.webp"
        }
      }
    ],
    "hp": 100,
    "types": [
      "water"
    ],
    "stage": "basic",
    "attacks": [
      {
        "name": {
          "ja": "ドレインフィン"
        },
        "cost": [
          "water",
          "normal"
        ],
        "damage": "20",
        "text": {
          "ja": "このポケモンのHPを「20」回復する。"
        }
      }
    ],
    "weaknesses": [
      {
        "type": "metal",
        "value": "x2"
      }
    ],
    "retreat_cost": 3,
    "flavor_text": {
      "ja": "寒冷地で ５匹ほどの 群れを 作って 暮らす。 雪や 氷に 含まれる ミネラルが 大好き。"
    }
  },
  {
    "id": "asia-sv7a-017",
    "set_id": "asia-sv7a",
    "number": "017",
    "category": "pokemon",
    "name": {
      "ja": "ハルクジラ"
    },
    "pokemon": [
      "0975"
    ],
    "illustrator": "Uta",
    "rarity": "common",
    "regulation_mark": "H",
    "variants": [
      {
        "id": "normal",
        "images": {
          "ja": "/images/cards/asia-sv7a/ja/017.webp"
        }
      }
    ],
    "hp": 180,
    "types": [
      "water"
    ],
    "stage": "stage1",
    "attacks": [
      {
        "name": {
          "ja": "デンジャーマウス"
        },
        "cost": [
          "water",
          "normal",
          "normal",
          "normal"
        ],
        "damage": "150",
        "text": {}
      }
    ],
    "weaknesses": [
      {
        "type": "metal",
        "value": "x2"
      }
    ],
    "retreat_cost": 3,
    "flavor_text": {
      "ja": "氷エネルギーの 集中する 上あごの ツノが 超低温になって 周囲を 凍らせる。"
    }
  },
  {
    "id": "asia-sv7a-018",
    "set_id": "asia-sv7a",
    "number": "018",
    "category": "pokemon",
    "name": {
      "ja": "ムチュール"
    },
    "pokemon": [
      "0238"
    ],
    "illustrator": "Saya Tsuruta",
    "rarity": "common",
    "regulation_mark": "H",
    "variants": [
      {
        "id": "normal",
        "images": {
          "ja": "/images/cards/asia-sv7a/ja/018.webp"
        }
      }
    ],
    "hp": 30,
    "types": [
      "psychic"
    ],
    "stage": "basic",
    "attacks": [
      {
        "name": {
          "ja": "るんるんキッス"
        },
        "cost": [],
        "damage": "",
        "text": {
          "ja": "自分の山札から「基本エネルギー」を2枚まで選び、ベンチポケモン1匹につける。そして山札を切る。"
        }
      }
    ],
    "weaknesses": [
      {
        "type": "dark",
        "value": "x2"
      }
    ],
    "resistances": [
      {
        "type": "fighting",
        "value": "－30"
      }
    ],
    "retreat_cost": 0,
    "flavor_text": {
      "ja": "ちょっとでも 顔が 汚れると 水浴び。 体の 汚れは あまり 気にしていないみたい。"
    }
  },
  {
    "id": "asia-sv7a-019",
    "set_id": "asia-sv7a",
    "number": "019",
    "category": "pokemon",
    "name": {
      "ja": "ラティアスex"
    },
    "pokemon": [
      "0380"
    ],
    "illustrator": "takuyoa",
    "rarity": "double_rare",
    "regulation_mark": "H",
    "variants": [
      {
        "id": "normal",
        "images": {
          "ja": "/images/cards/asia-sv7a/ja/019.webp"
        }
      }
    ],
    "hp": 210,
    "types": [
      "psychic"
    ],
    "stage": "basic",
    "rule_box": "EX",
    "attacks": [
      {
        "name": {
          "ja": "むげんのやいば"
        },
        "cost": [
          "psychic",
          "psychic",
          "normal"
        ],
        "damage": "200",
        "text": {
          "ja": "次の自分の番、このポケモンはワザが使えない。"
        }
      }
    ],
    "weaknesses": [
      {
        "type": "dark",
        "value": "x2"
      }
    ],
    "resistances": [
      {
        "type": "fighting",
        "value": "－30"
      }
    ],
    "retreat_cost": 2
  },
  {
    "id": "asia-sv7a-020",
    "set_id": "asia-sv7a",
    "number": "020",
    "category": "pokemon",
    "name": {
      "ja": "ラティオス"
    },
    "pokemon": [
      "0381"
    ],
    "illustrator": "kantaro",
    "rarity": "uncommon",
    "regulation_mark": "H",
    "variants": [
      {
        "id": "normal",
        "images": {
          "ja": "/images/cards/asia-sv7a/ja/020.webp"
        }
      }
    ],
    "hp": 120,
    "types": [
      "psychic"
    ],
    "stage": "basic",
    "attacks": [
      {
        "name": {
          "ja": "ちょくげきひこう"
        },
        "cost": [
          "psychic",
          "normal"
        ],
        "damage": "",
        "text": {
          "ja": "相手のポケモン1匹に、50ダメージ。［ベンチは弱点・抵抗力を計算しない。］"
        }
      },
      {
        "name": {
          "ja": "ジェットヘッド"
        },
        "cost": [
          "psychic",
          "psychic",
          "normal"
        ],
        "damage": "110",
        "text": {}
      }
    ],
    "weaknesses": [
      {
        "type": "dark",
        "value": "x2"
      }
    ],
    "resistances": [
      {
        "type": "fighting",
        "value": "－30"
      }
    ],
    "retreat_cost": 2,
    "flavor_text": {
      "ja": "高い 知能を 持つ ポケモン。 腕を 折りたたんで 飛べば ジェット機を 追い越す スピードだ。"
    }
  },
  {
    "id": "asia-sv7a-021",
    "set_id": "asia-sv7a",
    "number": "021",
    "category": "pokemon",
    "name": {
      "ja": "カプ・テテフ"
    },
    "pokemon": [
      "0786"
    ],
    "illustrator": "Natsumi Yoshida",
    "rarity": "rare",
    "regulation_mark": "H",
    "variants": [
      {
        "id": "normal",
        "images": {
          "ja": "/images/cards/asia-sv7a/ja/021.webp"
        }
      }
    ],
    "hp": 110,
    "types": [
      "psychic"
    ],
    "stage": "basic",
    "attacks": [
      {
        "name": {
          "ja": "まどわす"
        },
        "cost": [
          "normal",
          "normal"
        ],
        "damage": "20",
        "text": {
          "ja": "相手のバトルポケモンをこんらんにする。"
        }
      },
      {
        "name": {
          "ja": "メンタルクラッシュ"
        },
        "cost": [
          "psychic",
          "normal",
          "normal"
        ],
        "damage": "90＋",
        "text": {
          "ja": "相手のバトルポケモンがこんらんなら、90ダメージ追加。"
        }
      }
    ],
    "weaknesses": [
      {
        "type": "metal",
        "value": "x2"
      }
    ],
    "retreat_cost": 1,
    "flavor_text": {
      "ja": "ヒラヒラ 飛びまわり 不思議に 光る 鱗粉を 振りまく。 触れた者は たちまち 元気を 取り戻すという。"
    }
  },
  {
    "id": "asia-sv7a-022",
    "set_id": "asia-sv7a",
    "number": "022",
    "category": "pokemon",
    "name": {
      "ja": "ヒラヒナ"
    },
    "pokemon": [
      "0955"
    ],
    "illustrator": "buchi",
    "rarity": "common",
    "regulation_mark": "H",
    "variants": [
      {
        "id": "normal",
        "images": {
          "ja": "/images/cards/asia-sv7a/ja/022.webp"
        }
      }
    ],
    "hp": 40,
    "types": [
      "psychic"
    ],
    "stage": "basic",
    "attacks": [
      {
        "name": {
          "ja": "はねてかわす"
        },
        "cost": [
          "normal"
        ],
        "damage": "10",
        "text": {
          "ja": "コインを1回投げオモテなら、次の相手の番、このポケモンはワザのダメージや効果を受けない。"
        }
      }
    ],
    "weaknesses": [
      {
        "type": "dark",
        "value": "x2"
      }
    ],
    "resistances": [
      {
        "type": "fighting",
        "value": "－30"
      }
    ],
    "retreat_cost": 1,
    "flavor_text": {
      "ja": "荒れ地を 走りまわって 暮らす。 大好きな 木の実を 取られると 追いかけまわして 復讐する。"
    }
  },
  {
    "id": "asia-sv7a-023",
    "set_id": "asia-sv7a",
    "number": "023",
    "category": "pokemon",
    "name": {
      "ja": "クエスパトラ"
    },
    "pokemon": [
      "0956"
    ],
    "illustrator": "Anesaki Dynamic",
    "rarity": "uncommon",
    "regulation_mark": "H",
    "variants": [
      {
        "id": "normal",
        "images": {
          "ja": "/images/cards/asia-sv7a/ja/023.webp"
        }
      }
    ],
    "hp": 120,
    "types": [
      "psychic"
    ],
    "stage": "stage1",
    "attacks": [
      {
        "name": {
          "ja": "ミスティックアイ"
        },
        "cost": [
          "normal"
        ],
        "damage": "",
        "text": {
          "ja": "相手の進化しているポケモンを1匹選び、「進化カード」を1枚はがして退化させる。はがしたカードは、相手の手札にもどす。"
        }
      },
      {
        "name": {
          "ja": "スパイラルドレイン"
        },
        "cost": [
          "psychic",
          "normal"
        ],
        "damage": "60",
        "text": {
          "ja": "このポケモンのHPを「30」回復する。"
        }
      }
    ],
    "weaknesses": [
      {
        "type": "dark",
        "value": "x2"
      }
    ],
    "resistances": [
      {
        "type": "fighting",
        "value": "－30"
      }
    ],
    "retreat_cost": 1,
    "flavor_text": {
      "ja": "色とりどりの フリルの 隙間から サイコパワーを 放出して 時速２００キロで 疾走する。"
    }
  },
  {
    "id": "asia-sv7a-024",
    "set_id": "asia-sv7a",
    "number": "024",
    "category": "pokemon",
    "name": {
      "ja": "コレクレー"
    },
    "pokemon": [
      "0999"
    ],
    "illustrator": "Scav",
    "rarity": "common",
    "regulation_mark": "H",
    "variants": [
      {
        "id": "normal",
        "images": {
          "ja": "/images/cards/asia-sv7a/ja/024.webp"
        }
      }
    ],
    "hp": 70,
    "types": [
      "psychic"
    ],
    "stage": "basic",
    "attacks": [
      {
        "name": {
          "ja": "ちいさなおつかい"
        },
        "cost": [
          "normal"
        ],
        "damage": "",
        "text": {
          "ja": "自分の山札から基本エネルギーを2枚まで選び、相手に見せて、手札に加える。そして山札を切る。"
        }
      },
      {
        "name": {
          "ja": "たいあたり"
        },
        "cost": [
          "normal",
          "normal",
          "normal"
        ],
        "damage": "50",
        "text": {}
      }
    ],
    "weaknesses": [
      {
        "type": "dark",
        "value": "x2"
      }
    ],
    "resistances": [
      {
        "type": "fighting",
        "value": "－30"
      }
    ],
    "retreat_cost": 2,
    "flavor_text": {
      "ja": "古びた 宝箱の中に 棲む。 ポケモンと 気づかれず 道具屋の 片隅に 置かれていることがある。"
    }
  },
  {
    "id": "asia-sv7a-025",
    "set_id": "asia-sv7a",
    "number": "025",
    "category": "pokemon",
    "name": {
      "ja": "ナックラー"
    },
    "pokemon": [
      "0328"
    ],
    "illustrator": "Taiga Kayama",
    "rarity": "common",
    "regulation_mark": "H",
    "variants": [
      {
        "id": "normal",
        "images": {
          "ja": "/images/cards/asia-sv7a/ja/025.webp"
        }
      }
    ],
    "hp": 60,
    "types": [
      "fighting"
    ],
    "stage": "basic",
    "attacks": [
      {
        "name": {
          "ja": "なかまをよぶ"
        },
        "cost": [
          "normal"
        ],
        "damage": "",
        "text": {
          "ja": "自分の山札からたねポケモンを2枚まで選び、ベンチに出す。そして山札を切る。"
        }
      },
      {
        "name": {
          "ja": "かみつく"
        },
        "cost": [
          "fighting",
          "normal"
        ],
        "damage": "20",
        "text": {}
      }
    ],
    "weaknesses": [
      {
        "type": "grass",
        "value": "x2"
      }
    ],
    "retreat_cost": 1,
    "flavor_text": {
      "ja": "大きな あごで 邪魔な 岩を 砕きながら 砂を 掘る。 巣穴の 形は スリ鉢状。"
    }
  },
  {
    "id": "asia-sv7a-026",
    "set_id": "asia-sv7a",
    "number": "026",
    "category": "pokemon",
    "name": {
      "ja": "ビブラーバ"
    },
    "pokemon": [
      "0329"
    ],
    "illustrator": "Teeziro",
    "rarity": "common",
    "regulation_mark": "H",
    "variants": [
      {
        "id": "normal",
        "images": {
          "ja": "/images/cards/asia-sv7a/ja/026.webp"
        }
      }
    ],
    "hp": 90,
    "types": [
      "fighting"
    ],
    "stage": "stage1",
    "attacks": [
      {
        "name": {
          "ja": "いやなおと"
        },
        "cost": [
          "normal"
        ],
        "damage": "",
        "text": {
          "ja": "次の自分の番、このワザを受けたポケモンが受けるワザのダメージは「+50」される。"
        }
      },
      {
        "name": {
          "ja": "カッターウインド"
        },
        "cost": [
          "fighting",
          "normal"
        ],
        "damage": "50",
        "text": {}
      }
    ],
    "weaknesses": [
      {
        "type": "grass",
        "value": "x2"
      }
    ],
    "retreat_cost": 1,
    "flavor_text": {
      "ja": "翅を 激しく 振動させて 超音波を 発生。 気絶した 獲物を 消化液で 溶かす。"
    }
  },
  {
    "id": "asia-sv7a-027",
    "set_id": "asia-sv7a",
    "number": "027",
    "category": "pokemon",
    "name": {
      "ja": "フライゴンex"
    },
    "pokemon": [],
    "illustrator": "5ban Graphics",
    "rarity": "double_rare",
    "regulation_mark": "H",
    "variants": [
      {
        "id": "normal",
        "images": {
          "ja": "/images/cards/asia-sv7a/ja/027.webp"
        }
      }
    ],
    "hp": 310,
    "types": [
      "fighting"
    ],
    "stage": "stage2",
    "rule_box": "EX",
    "attacks": [
      {
        "name": {
          "ja": "ストームバック"
        },
        "cost": [
          "fighting"
        ],
        "damage": "130",
        "text": {
          "ja": "のぞむなら、このポケモンをベンチポケモンと入れ替える。"
        }
      },
      {
        "name": {
          "ja": "ペリドットソニック"
        },
        "cost": [
          "water",
          "fighting",
          "metal"
        ],
        "damage": "",
        "text": {
          "ja": "相手の「ポケモンex・V」全員に、それぞれ100ダメージ。このワザのダメージは弱点・抵抗力を計算しない。"
        }
      }
    ],
    "weaknesses": [
      {
        "type": "grass",
        "value": "x2"
      }
    ],
    "retreat_cost": 1
  },
  {
    "id": "asia-sv7a-028",
    "set_id": "asia-sv7a",
    "number": "028",
    "category": "pokemon",
    "name": {
      "ja": "モグリュー"
    },
    "pokemon": [
      "0529"
    ],
    "illustrator": "Ounishi",
    "rarity": "common",
    "regulation_mark": "H",
    "variants": [
      {
        "id": "normal",
        "images": {
          "ja": "/images/cards/asia-sv7a/ja/028.webp"
        }
      }
    ],
    "hp": 70,
    "types": [
      "fighting"
    ],
    "stage": "basic",
    "attacks": [
      {
        "name": {
          "ja": "ほるほる"
        },
        "cost": [
          "normal"
        ],
        "damage": "",
        "text": {
          "ja": "相手の山札を上から1枚トラッシュする。"
        }
      },
      {
        "name": {
          "ja": "どろかけ"
        },
        "cost": [
          "fighting"
        ],
        "damage": "10",
        "text": {}
      }
    ],
    "weaknesses": [
      {
        "type": "grass",
        "value": "x2"
      }
    ],
    "retreat_cost": 2,
    "flavor_text": {
      "ja": "両手の ツメを 重ね合わせて 体を 高速 回転させると 猛スピードで 地中を 進む。"
    }
  },
  {
    "id": "asia-sv7a-029",
    "set_id": "asia-sv7a",
    "number": "029",
    "category": "pokemon",
    "name": {
      "ja": "ドリュウズ"
    },
    "pokemon": [
      "0530"
    ],
    "illustrator": "Yuya Oka",
    "rarity": "common",
    "regulation_mark": "H",
    "variants": [
      {
        "id": "normal",
        "images": {
          "ja": "/images/cards/asia-sv7a/ja/029.webp"
        }
      }
    ],
    "hp": 120,
    "types": [
      "fighting"
    ],
    "stage": "stage1",
    "attacks": [
      {
        "name": {
          "ja": "あなほりクロー"
        },
        "cost": [
          "normal"
        ],
        "damage": "20",
        "text": {
          "ja": "相手の山札を上から1枚トラッシュする。"
        }
      },
      {
        "name": {
          "ja": "ドリルスマッシュ"
        },
        "cost": [
          "fighting",
          "normal"
        ],
        "damage": "60＋",
        "text": {
          "ja": "自分のベンチにポケモンがいるなら、80ダメージ追加。"
        }
      }
    ],
    "weaknesses": [
      {
        "type": "grass",
        "value": "x2"
      }
    ],
    "retreat_cost": 2,
    "flavor_text": {
      "ja": "鋼に 進化した ドリルは 鉄板を 貫く 破壊力。 トンネル工事で 大活躍する。"
    }
  },
  {
    "id": "asia-sv7a-030",
    "set_id": "asia-sv7a",
    "number": "030",
    "category": "pokemon",
    "name": {
      "ja": "ランドロス"
    },
    "pokemon": [
      "0645"
    ],
    "illustrator": "Souichirou Gunjima",
    "rarity": "rare",
    "regulation_mark": "H",
    "variants": [
      {
        "id": "normal",
        "images": {
          "ja": "/images/cards/asia-sv7a/ja/030.webp"
        }
      }
    ],
    "hp": 130,
    "types": [
      "fighting"
    ],
    "stage": "basic",
    "attacks": [
      {
        "name": {
          "ja": "きあいのこぶし"
        },
        "cost": [
          "fighting"
        ],
        "damage": "30",
        "text": {
          "ja": "自分のトラッシュからエネルギーを1枚選び、このポケモンにつける。"
        }
      },
      {
        "name": {
          "ja": "バスタースイング"
        },
        "cost": [
          "fighting",
          "normal",
          "normal",
          "normal"
        ],
        "damage": "130",
        "text": {
          "ja": "このワザのダメージは抵抗力を計算しない。"
        }
      }
    ],
    "weaknesses": [
      {
        "type": "grass",
        "value": "x2"
      }
    ],
    "retreat_cost": 2,
    "flavor_text": {
      "ja": "ランドロスが 訪れる 土地は 作物が たくさん 実るため 畑の神様 と 言われている。"
    }
  },
  {
    "id": "asia-sv7a-031",
    "set_id": "asia-sv7a",
    "number": "031",
    "category": "pokemon",
    "name": {
      "ja": "ナゲツケサル"
    },
    "pokemon": [
      "0766"
    ],
    "illustrator": "Teeziro",
    "rarity": "uncommon",
    "regulation_mark": "H",
    "variants": [
      {
        "id": "normal",
        "images": {
          "ja": "/images/cards/asia-sv7a/ja/031.webp"
        }
      }
    ],
    "hp": 110,
    "types": [
      "fighting"
    ],
    "stage": "basic",
    "attacks": [
      {
        "name": {
          "ja": "れんけいスロー"
        },
        "cost": [
          "fighting",
          "normal"
        ],
        "damage": "20×",
        "text": {
          "ja": "自分の場のたねポケモンの数×20ダメージ。"
        }
      }
    ],
    "weaknesses": [
      {
        "type": "psychic",
        "value": "x2"
      }
    ],
    "retreat_cost": 1,
    "flavor_text": {
      "ja": "ボスが 選んだ １０匹で 狩りに 出かけ 取ってきた エサを 群れの 仲間で 平等に 分け合う。"
    }
  },
  {
    "id": "asia-sv7a-032",
    "set_id": "asia-sv7a",
    "number": "032",
    "category": "pokemon",
    "name": {
      "ja": "タタッコ"
    },
    "pokemon": [
      "0852"
    ],
    "illustrator": "Shimaris Yukichi",
    "rarity": "common",
    "regulation_mark": "H",
    "variants": [
      {
        "id": "normal",
        "images": {
          "ja": "/images/cards/asia-sv7a/ja/032.webp"
        }
      }
    ],
    "hp": 70,
    "types": [
      "fighting"
    ],
    "stage": "basic",
    "attacks": [
      {
        "name": {
          "ja": "ちょっとつっこむ"
        },
        "cost": [
          "fighting"
        ],
        "damage": "30",
        "text": {
          "ja": "このポケモンにも10ダメージ。"
        }
      }
    ],
    "weaknesses": [
      {
        "type": "psychic",
        "value": "x2"
      }
    ],
    "retreat_cost": 2,
    "flavor_text": {
      "ja": "餌を 求め 地上に 上がる。 好奇心旺盛で 目にしたものは とりあえず 触手で 殴る。"
    }
  },
  {
    "id": "asia-sv7a-033",
    "set_id": "asia-sv7a",
    "number": "033",
    "category": "pokemon",
    "name": {
      "ja": "オトスパス"
    },
    "pokemon": [
      "0853"
    ],
    "illustrator": "KEIICHIRO ITO",
    "rarity": "common",
    "regulation_mark": "H",
    "variants": [
      {
        "id": "normal",
        "images": {
          "ja": "/images/cards/asia-sv7a/ja/033.webp"
        }
      }
    ],
    "hp": 140,
    "types": [
      "fighting"
    ],
    "stage": "stage1",
    "attacks": [
      {
        "name": {
          "ja": "チョップ"
        },
        "cost": [
          "fighting"
        ],
        "damage": "40",
        "text": {}
      },
      {
        "name": {
          "ja": "テンタクルレイジ"
        },
        "cost": [
          "fighting",
          "fighting",
          "normal"
        ],
        "damage": "130",
        "text": {
          "ja": "このワザは、このポケモンにダメカンがのっているなら、エネルギー1個で使える。"
        }
      }
    ],
    "weaknesses": [
      {
        "type": "psychic",
        "value": "x2"
      }
    ],
    "retreat_cost": 3,
    "flavor_text": {
      "ja": "全身が 筋肉の 塊。 触手を 使って 繰りだす 絞め技の 威力は 凄まじい。"
    }
  },
  {
    "id": "asia-sv7a-034",
    "set_id": "asia-sv7a",
    "number": "034",
    "category": "pokemon",
    "name": {
      "ja": "エアームド"
    },
    "pokemon": [
      "0227"
    ],
    "illustrator": "kawayoo",
    "rarity": "common",
    "regulation_mark": "H",
    "variants": [
      {
        "id": "normal",
        "images": {
          "ja": "/images/cards/asia-sv7a/ja/034.webp"
        }
      }
    ],
    "hp": 110,
    "types": [
      "metal"
    ],
    "stage": "basic",
    "attacks": [
      {
        "name": {
          "ja": "はがねのつばさ"
        },
        "cost": [
          "metal",
          "normal"
        ],
        "damage": "50",
        "text": {
          "ja": "次の相手の番、このポケモンが受けるワザのダメージは「-30」される。"
        }
      }
    ],
    "weaknesses": [
      {
        "type": "lightning",
        "value": "x2"
      }
    ],
    "resistances": [
      {
        "type": "fighting",
        "value": "－30"
      }
    ],
    "retreat_cost": 1,
    "flavor_text": {
      "ja": "抜け落ちた 羽根は 薄く 鋭いので 刀として 使われていたことも あったらしい。"
    }
  },
  {
    "id": "asia-sv7a-035",
    "set_id": "asia-sv7a",
    "number": "035",
    "category": "pokemon",
    "name": {
      "ja": "クレッフィ"
    },
    "pokemon": [
      "0707"
    ],
    "illustrator": "mingo",
    "rarity": "common",
    "regulation_mark": "H",
    "variants": [
      {
        "id": "normal",
        "images": {
          "ja": "/images/cards/asia-sv7a/ja/035.webp"
        }
      }
    ],
    "hp": 70,
    "types": [
      "metal"
    ],
    "stage": "basic",
    "attacks": [
      {
        "name": {
          "ja": "さしこみドロー"
        },
        "cost": [
          "normal"
        ],
        "damage": "",
        "text": {
          "ja": "自分の手札を1枚トラッシュする。その後、自分の山札を2枚引く。"
        }
      },
      {
        "name": {
          "ja": "ひっかける"
        },
        "cost": [
          "normal"
        ],
        "damage": "20",
        "text": {}
      }
    ],
    "weaknesses": [
      {
        "type": "fire",
        "value": "x2"
      }
    ],
    "resistances": [
      {
        "type": "grass",
        "value": "－30"
      }
    ],
    "retreat_cost": 1,
    "flavor_text": {
      "ja": "昔の 貴族は 金庫の カギを 管理させる クレッフィを 代々 引き継ぎ 大切に 扱った。"
    }
  },
  {
    "id": "asia-sv7a-036",
    "set_id": "asia-sv7a",
    "number": "036",
    "category": "pokemon",
    "name": {
      "ja": "ジュラルドン"
    },
    "pokemon": [
      "0884"
    ],
    "illustrator": "Tonji Matsuno",
    "rarity": "common",
    "regulation_mark": "H",
    "variants": [
      {
        "id": "normal",
        "images": {
          "ja": "/images/cards/asia-sv7a/ja/036.webp"
        }
      }
    ],
    "hp": 130,
    "types": [
      "metal"
    ],
    "stage": "basic",
    "attacks": [
      {
        "name": {
          "ja": "がちんこ"
        },
        "cost": [
          "metal",
          "metal"
        ],
        "damage": "50",
        "text": {}
      },
      {
        "name": {
          "ja": "ジュラルビーム"
        },
        "cost": [
          "metal",
          "metal",
          "metal"
        ],
        "damage": "130",
        "text": {
          "ja": "このポケモンについているエネルギーを2個選び、トラッシュする。"
        }
      }
    ],
    "weaknesses": [
      {
        "type": "fire",
        "value": "x2"
      }
    ],
    "resistances": [
      {
        "type": "grass",
        "value": "－30"
      }
    ],
    "retreat_cost": 2,
    "flavor_text": {
      "ja": "金属の ボディは 頑丈だが 熱が こもってしまうので 尻尾の スリットから 放熱している。"
    }
  },
  {
    "id": "asia-sv7a-037",
    "set_id": "asia-sv7a",
    "number": "037",
    "category": "pokemon",
    "name": {
      "ja": "ブリジュラスex"
    },
    "pokemon": [
      "1018"
    ],
    "illustrator": "5ban Graphics",
    "rarity": "double_rare",
    "regulation_mark": "H",
    "variants": [
      {
        "id": "normal",
        "images": {
          "ja": "/images/cards/asia-sv7a/ja/037.webp"
        }
      }
    ],
    "hp": 300,
    "types": [
      "metal"
    ],
    "stage": "stage1",
    "rule_box": "EX",
    "attacks": [
      {
        "name": {
          "ja": "メタルディフェンダー"
        },
        "cost": [
          "metal",
          "metal",
          "metal"
        ],
        "damage": "220",
        "text": {
          "ja": "次の相手の番、このポケモンの弱点は、すべてなくなる。"
        }
      }
    ],
    "weaknesses": [
      {
        "type": "fire",
        "value": "x2"
      }
    ],
    "resistances": [
      {
        "type": "grass",
        "value": "－30"
      }
    ],
    "retreat_cost": 2
  },
  {
    "id": "asia-sv7a-038",
    "set_id": "asia-sv7a",
    "number": "038",
    "category": "pokemon",
    "name": {
      "ja": "サーフゴー"
    },
    "pokemon": [
      "1000"
    ],
    "illustrator": "Dsuke",
    "rarity": "uncommon",
    "regulation_mark": "H",
    "variants": [
      {
        "id": "normal",
        "images": {
          "ja": "/images/cards/asia-sv7a/ja/038.webp"
        }
      }
    ],
    "hp": 130,
    "types": [
      "metal"
    ],
    "stage": "stage1",
    "attacks": [
      {
        "name": {
          "ja": "リッチストライク"
        },
        "cost": [
          "metal"
        ],
        "damage": "30＋",
        "text": {
          "ja": "この番、このポケモンが「コレクレー」から進化していたなら、90ダメージ追加。"
        }
      },
      {
        "name": {
          "ja": "サーフリターン"
        },
        "cost": [
          "normal",
          "normal",
          "normal"
        ],
        "damage": "100",
        "text": {
          "ja": "のぞむなら、このポケモンと、ついているすべてのカードを、自分の山札にもどして切る。"
        }
      }
    ],
    "weaknesses": [
      {
        "type": "fire",
        "value": "x2"
      }
    ],
    "resistances": [
      {
        "type": "grass",
        "value": "－30"
      }
    ],
    "retreat_cost": 2,
    "flavor_text": {
      "ja": "コインが 積みあがって 作られた 体は 頑丈。 コインを 連射して 敵を 圧倒する。"
    }
  },
  {
    "id": "asia-sv7a-039",
    "set_id": "asia-sv7a",
    "number": "039",
    "category": "pokemon",
    "name": {
      "ja": "テツノカシラ"
    },
    "pokemon": [
      "1023"
    ],
    "illustrator": "akagi",
    "rarity": "rare",
    "regulation_mark": "H",
    "variants": [
      {
        "id": "normal",
        "images": {
          "ja": "/images/cards/asia-sv7a/ja/039.webp"
        }
      }
    ],
    "hp": 130,
    "types": [
      "metal"
    ],
    "stage": "basic",
    "attacks": [
      {
        "name": {
          "ja": "デリートスラッシュ"
        },
        "cost": [
          "metal",
          "normal"
        ],
        "damage": "40＋",
        "text": {
          "ja": "相手のベンチポケモンの数が3匹以上なら、80ダメージ追加。"
        }
      },
      {
        "name": {
          "ja": "スライスブレード"
        },
        "cost": [
          "metal",
          "normal",
          "normal"
        ],
        "damage": "100",
        "text": {}
      }
    ],
    "weaknesses": [
      {
        "type": "fire",
        "value": "x2"
      }
    ],
    "resistances": [
      {
        "type": "grass",
        "value": "－30"
      }
    ],
    "retreat_cost": 2,
    "flavor_text": {
      "ja": "光る 刃を 撃ちだし あたりの すべてを 切り裂いたらしいが ほかに 情報はなく 正体不明。"
    }
  },
  {
    "id": "asia-sv7a-040",
    "set_id": "asia-sv7a",
    "number": "040",
    "category": "pokemon",
    "name": {
      "ja": "アローラ ナッシーex"
    },
    "pokemon": [
      "0103"
    ],
    "illustrator": "aky CG Works",
    "rarity": "double_rare",
    "regulation_mark": "H",
    "variants": [
      {
        "id": "normal",
        "images": {
          "ja": "/images/cards/asia-sv7a/ja/040.webp"
        }
      }
    ],
    "hp": 300,
    "types": [
      "dragon"
    ],
    "stage": "stage1",
    "rule_box": "EX",
    "attacks": [
      {
        "name": {
          "ja": "トロピカルフィーバー"
        },
        "cost": [
          "grass",
          "water"
        ],
        "damage": "150",
        "text": {
          "ja": "自分の手札から基本エネルギーを好きなだけ選び、自分のポケモンに好きなようにつける。"
        }
      },
      {
        "name": {
          "ja": "ブンブンスフェーン"
        },
        "cost": [
          "grass",
          "water",
          "fighting"
        ],
        "damage": "",
        "text": {
          "ja": "コインを1回投げオモテなら、相手のバトル場のたねポケモンをきぜつさせる。ウラなら、相手のベンチのたねポケモンを1匹選び、きぜつさせる。"
        }
      }
    ],
    "retreat_cost": 3
  },
  {
    "id": "asia-sv7a-041",
    "set_id": "asia-sv7a",
    "number": "041",
    "category": "pokemon",
    "name": {
      "ja": "チルタリス"
    },
    "pokemon": [
      "0334"
    ],
    "illustrator": "rika",
    "rarity": "uncommon",
    "regulation_mark": "H",
    "variants": [
      {
        "id": "normal",
        "images": {
          "ja": "/images/cards/asia-sv7a/ja/041.webp"
        }
      }
    ],
    "hp": 120,
    "types": [
      "dragon"
    ],
    "stage": "stage1",
    "attacks": [
      {
        "name": {
          "ja": "ハミングチャージ"
        },
        "cost": [
          "water"
        ],
        "damage": "",
        "text": {
          "ja": "自分の山札から基本エネルギーを2枚まで選び、自分のポケモンに好きなようにつける。そして山札を切る。"
        }
      },
      {
        "name": {
          "ja": "コットンウイング"
        },
        "cost": [
          "water",
          "metal"
        ],
        "damage": "100",
        "text": {
          "ja": "コインを1回投げオモテなら、次の相手の番、このポケモンはワザのダメージを受けない。"
        }
      }
    ],
    "retreat_cost": 1,
    "flavor_text": {
      "ja": "晴れた日 綿雲に まぎれながら 大空を 自由に 飛びまわり 美しい ソプラノで 歌う。"
    }
  },
  {
    "id": "asia-sv7a-042",
    "set_id": "asia-sv7a",
    "number": "042",
    "category": "pokemon",
    "name": {
      "ja": "ディアルガ"
    },
    "pokemon": [
      "0483"
    ],
    "illustrator": "Takumi Wada",
    "rarity": "rare",
    "regulation_mark": "H",
    "variants": [
      {
        "id": "normal",
        "images": {
          "ja": "/images/cards/asia-sv7a/ja/042.webp"
        }
      }
    ],
    "hp": 130,
    "types": [
      "dragon"
    ],
    "stage": "basic",
    "attacks": [
      {
        "name": {
          "ja": "タイムコントロール"
        },
        "cost": [
          "normal"
        ],
        "damage": "",
        "text": {
          "ja": "自分の山札から好きなカードを2枚選ぶ。残りの山札を切り、選んだカードを好きな順番に入れ替えて、山札の上にもどす。"
        }
      },
      {
        "name": {
          "ja": "バスターテール"
        },
        "cost": [
          "psychic",
          "metal",
          "normal"
        ],
        "damage": "160",
        "text": {}
      }
    ],
    "retreat_cost": 2,
    "flavor_text": {
      "ja": "ディアルガが 生まれたことで 時間が 動き出したという 伝説を 持つ ポケモン。"
    }
  },
  {
    "id": "asia-sv7a-043",
    "set_id": "asia-sv7a",
    "number": "043",
    "category": "pokemon",
    "name": {
      "ja": "パルキア"
    },
    "pokemon": [
      "0484"
    ],
    "illustrator": "danciao",
    "rarity": "rare",
    "regulation_mark": "H",
    "variants": [
      {
        "id": "normal",
        "images": {
          "ja": "/images/cards/asia-sv7a/ja/043.webp"
        }
      }
    ],
    "hp": 130,
    "types": [
      "dragon"
    ],
    "stage": "basic",
    "attacks": [
      {
        "name": {
          "ja": "スペースクラッシュ"
        },
        "cost": [
          "grass",
          "water"
        ],
        "damage": "40×",
        "text": {
          "ja": "このポケモンについている基本エネルギーの数×40ダメージ。"
        }
      }
    ],
    "retreat_cost": 2,
    "flavor_text": {
      "ja": "並行して 並ぶ 空間の 狭間に 住むと 言われている。 神話に 登場する ポケモン。"
    }
  },
  {
    "id": "asia-sv7a-044",
    "set_id": "asia-sv7a",
    "number": "044",
    "category": "pokemon",
    "name": {
      "ja": "バクガメス"
    },
    "pokemon": [
      "0776"
    ],
    "illustrator": "Rianti Hidayat",
    "rarity": "uncommon",
    "regulation_mark": "H",
    "variants": [
      {
        "id": "normal",
        "images": {
          "ja": "/images/cards/asia-sv7a/ja/044.webp"
        }
      }
    ],
    "hp": 120,
    "types": [
      "dragon"
    ],
    "stage": "basic",
    "attacks": [
      {
        "name": {
          "ja": "こがしつくす"
        },
        "cost": [
          "fire"
        ],
        "damage": "",
        "text": {
          "ja": "相手のバトル場の「ポケモンex」についているエネルギーを1個選び、トラッシュする。"
        }
      },
      {
        "name": {
          "ja": "ばくねつスタンプ"
        },
        "cost": [
          "fighting",
          "normal",
          "normal"
        ],
        "damage": "100",
        "text": {}
      }
    ],
    "retreat_cost": 3,
    "flavor_text": {
      "ja": "爆薬で コーティングされた 甲羅を 背負う。 攻撃してきた 敵を 大爆発で 返り討ち。"
    }
  },
  {
    "id": "asia-sv7a-045",
    "set_id": "asia-sv7a",
    "number": "045",
    "category": "pokemon",
    "name": {
      "ja": "カジッチュ"
    },
    "pokemon": [
      "0840"
    ],
    "illustrator": "Yuka Morii",
    "rarity": "common",
    "regulation_mark": "H",
    "variants": [
      {
        "id": "normal",
        "images": {
          "ja": "/images/cards/asia-sv7a/ja/045.webp"
        }
      }
    ],
    "hp": 40,
    "types": [
      "dragon"
    ],
    "stage": "basic",
    "attacks": [
      {
        "name": {
          "ja": "えいようそ"
        },
        "cost": [
          "normal"
        ],
        "damage": "",
        "text": {
          "ja": "自分のポケモン1匹のHPを「30」回復する。"
        }
      },
      {
        "name": {
          "ja": "ころばす"
        },
        "cost": [
          "grass",
          "fire"
        ],
        "damage": "20＋",
        "text": {
          "ja": "コインを1回投げオモテなら、30ダメージ追加。"
        }
      }
    ],
    "retreat_cost": 1,
    "flavor_text": {
      "ja": "りんごの 中で 暮らしている。 りんごが なくなると 体の 水分が 抜けて 弱ってしまう。"
    }
  },
  {
    "id": "asia-sv7a-046",
    "set_id": "asia-sv7a",
    "number": "046",
    "category": "pokemon",
    "name": {
      "ja": "アップリュー"
    },
    "pokemon": [
      "0841"
    ],
    "illustrator": "GOTO minori",
    "rarity": "uncommon",
    "regulation_mark": "H",
    "variants": [
      {
        "id": "normal",
        "images": {
          "ja": "/images/cards/asia-sv7a/ja/046.webp"
        }
      }
    ],
    "hp": 80,
    "types": [
      "dragon"
    ],
    "stage": "stage1",
    "attacks": [
      {
        "name": {
          "ja": "サワースピット"
        },
        "cost": [
          "normal"
        ],
        "damage": "20×",
        "text": {
          "ja": "相手のバトルポケモンにのっているダメカンの数×20ダメージ。"
        }
      },
      {
        "name": {
          "ja": "スピードひこう"
        },
        "cost": [
          "grass",
          "fire"
        ],
        "damage": "70",
        "text": {}
      }
    ],
    "retreat_cost": 1,
    "flavor_text": {
      "ja": "体液で りんごを 補修する。 歴戦の 強者の りんごは 全体的に 粘土色。"
    }
  },
  {
    "id": "asia-sv7a-047",
    "set_id": "asia-sv7a",
    "number": "047",
    "category": "pokemon",
    "name": {
      "ja": "タルップル"
    },
    "pokemon": [
      "0842"
    ],
    "illustrator": "Oswaldo KATO",
    "rarity": "uncommon",
    "regulation_mark": "H",
    "variants": [
      {
        "id": "normal",
        "images": {
          "ja": "/images/cards/asia-sv7a/ja/047.webp"
        }
      }
    ],
    "hp": 90,
    "types": [
      "dragon"
    ],
    "stage": "stage1",
    "attacks": [
      {
        "name": {
          "ja": "スイートメルト"
        },
        "cost": [
          "normal",
          "normal"
        ],
        "damage": "50",
        "text": {
          "ja": "次の相手の番、このワザを受けたポケモンは、ワザが使えない。"
        }
      },
      {
        "name": {
          "ja": "ワイルドタックル"
        },
        "cost": [
          "grass",
          "fire"
        ],
        "damage": "130",
        "text": {
          "ja": "このポケモンにも20ダメージ。"
        }
      }
    ],
    "retreat_cost": 3,
    "flavor_text": {
      "ja": "背中の 甘い蜜を 舐め取りに やって来る グルトンに ベトベトの 蜜を 吐きかけ 退ける。"
    }
  },
  {
    "id": "asia-sv7a-048",
    "set_id": "asia-sv7a",
    "number": "048",
    "category": "pokemon",
    "name": {
      "ja": "チルット"
    },
    "pokemon": [
      "0333"
    ],
    "illustrator": "sowsow",
    "rarity": "common",
    "regulation_mark": "H",
    "variants": [
      {
        "id": "normal",
        "images": {
          "ja": "/images/cards/asia-sv7a/ja/048.webp"
        }
      }
    ],
    "hp": 50,
    "types": [
      "normal"
    ],
    "stage": "basic",
    "attacks": [
      {
        "name": {
          "ja": "チャームボイス"
        },
        "cost": [
          "normal"
        ],
        "damage": "10",
        "text": {
          "ja": "相手のバトルポケモンをこんらんにする。"
        }
      }
    ],
    "weaknesses": [
      {
        "type": "lightning",
        "value": "x2"
      }
    ],
    "resistances": [
      {
        "type": "fighting",
        "value": "－30"
      }
    ],
    "retreat_cost": 1,
    "flavor_text": {
      "ja": "自分も まわりも きれいでないと 落ち着かない 性格。 汚れを 見つけると 羽で ふき取る。"
    }
  },
  {
    "id": "asia-sv7a-049",
    "set_id": "asia-sv7a",
    "number": "049",
    "category": "pokemon",
    "name": {
      "ja": "ワシボン"
    },
    "pokemon": [
      "0627"
    ],
    "illustrator": "Nakamura Ippan",
    "rarity": "common",
    "regulation_mark": "H",
    "variants": [
      {
        "id": "normal",
        "images": {
          "ja": "/images/cards/asia-sv7a/ja/049.webp"
        }
      }
    ],
    "hp": 70,
    "types": [
      "normal"
    ],
    "stage": "basic",
    "attacks": [
      {
        "name": {
          "ja": "はばたく"
        },
        "cost": [
          "normal",
          "normal"
        ],
        "damage": "30",
        "text": {}
      }
    ],
    "weaknesses": [
      {
        "type": "lightning",
        "value": "x2"
      }
    ],
    "resistances": [
      {
        "type": "fighting",
        "value": "－30"
      }
    ],
    "retreat_cost": 1,
    "flavor_text": {
      "ja": "尖ったツメを 獲物に 突き立て ついばんでいる。 木の実も 食べるが 基本的に 肉食のポケモン。"
    }
  },
  {
    "id": "asia-sv7a-050",
    "set_id": "asia-sv7a",
    "number": "050",
    "category": "pokemon",
    "name": {
      "ja": "ウォーグル"
    },
    "pokemon": [
      "0628"
    ],
    "illustrator": "Anesaki Dynamic",
    "rarity": "uncommon",
    "regulation_mark": "H",
    "variants": [
      {
        "id": "normal",
        "images": {
          "ja": "/images/cards/asia-sv7a/ja/050.webp"
        }
      }
    ],
    "hp": 130,
    "types": [
      "normal"
    ],
    "stage": "stage1",
    "attacks": [
      {
        "name": {
          "ja": "ひきずりだす"
        },
        "cost": [
          "normal",
          "normal"
        ],
        "damage": "",
        "text": {
          "ja": "相手のベンチポケモンを1匹選び、バトルポケモンと入れ替える。その後、新しく出てきたポケモンに40ダメージ。"
        }
      },
      {
        "name": {
          "ja": "ブラストウインド"
        },
        "cost": [
          "normal",
          "normal",
          "normal"
        ],
        "damage": "120",
        "text": {}
      }
    ],
    "weaknesses": [
      {
        "type": "lightning",
        "value": "x2"
      }
    ],
    "resistances": [
      {
        "type": "fighting",
        "value": "－30"
      }
    ],
    "retreat_cost": 1,
    "flavor_text": {
      "ja": "仲間の ためなら どれだけ 傷つこうとも 戦いを やめない 勇敢な 大空の 戦士。"
    }
  },
  {
    "id": "asia-sv7a-051",
    "set_id": "asia-sv7a",
    "number": "051",
    "category": "pokemon",
    "name": {
      "ja": "モトトカゲex"
    },
    "pokemon": [],
    "illustrator": "5ban Graphics",
    "rarity": "double_rare",
    "regulation_mark": "H",
    "variants": [
      {
        "id": "normal",
        "images": {
          "ja": "/images/cards/asia-sv7a/ja/051.webp"
        }
      }
    ],
    "hp": 210,
    "types": [
      "normal"
    ],
    "stage": "basic",
    "rule_box": "EX",
    "attacks": [
      {
        "name": {
          "ja": "ブレイクスルー"
        },
        "cost": [
          "normal",
          "normal",
          "normal"
        ],
        "damage": "130",
        "text": {
          "ja": "相手のベンチポケモン1匹にも、30ダメージ。［ベンチは弱点・抵抗力を計算しない。］"
        }
      },
      {
        "name": {
          "ja": "ジルコンロード"
        },
        "cost": [
          "grass",
          "fire",
          "psychic"
        ],
        "damage": "180",
        "text": {
          "ja": "のぞむなら、自分の山札を5枚引く。"
        }
      }
    ],
    "weaknesses": [
      {
        "type": "fighting",
        "value": "x2"
      }
    ],
    "retreat_cost": 1
  },
  {
    "id": "asia-sv7a-052",
    "set_id": "asia-sv7a",
    "number": "052",
    "category": "trainer",
    "name": {
      "ja": "エネルギー転送PRO"
    },
    "pokemon": [],
    "illustrator": "Toyste Beach",
    "rarity": "none",
    "regulation_mark": "H",
    "variants": [
      {
        "id": "normal",
        "images": {
          "ja": "/images/cards/asia-sv7a/ja/052.webp"
        }
      }
    ],
    "trainer_type": "item",
    "rules_text": {
      "ja": "自分の山札から、それぞれちがうタイプの基本エネルギーを好きなだけ選び、相手に見せて、手札に加える。そして山札を切る。"
    }
  },
  {
    "id": "asia-sv7a-053",
    "set_id": "asia-sv7a",
    "number": "053",
    "category": "trainer",
    "name": {
      "ja": "おたすけベル"
    },
    "pokemon": [],
    "illustrator": "Ayaka Yoshida",
    "rarity": "uncommon",
    "regulation_mark": "H",
    "variants": [
      {
        "id": "normal",
        "images": {
          "ja": "/images/cards/asia-sv7a/ja/053.webp"
        }
      }
    ],
    "trainer_type": "item",
    "rules_text": {
      "ja": "このカードは、後攻プレイヤーの最初の番しか使えない。\n\n自分の山札からサポートを1枚選び、相手に見せて、手札に加える。そして山札を切る。"
    }
  },
  {
    "id": "asia-sv7a-054",
    "set_id": "asia-sv7a",
    "number": "054",
    "category": "trainer",
    "name": {
      "ja": "ダークボール"
    },
    "pokemon": [],
    "illustrator": "Studio Bora Inc.",
    "rarity": "uncommon",
    "regulation_mark": "H",
    "variants": [
      {
        "id": "normal",
        "images": {
          "ja": "/images/cards/asia-sv7a/ja/054.webp"
        }
      }
    ],
    "trainer_type": "item",
    "rules_text": {
      "ja": "自分の山札を下から7枚見て、その中からポケモンを1枚選び、相手に見せて、手札に加える。残りのカードは山札にもどして切る。"
    }
  },
  {
    "id": "asia-sv7a-055",
    "set_id": "asia-sv7a",
    "number": "055",
    "category": "trainer",
    "name": {
      "ja": "ぼうがいレター"
    },
    "pokemon": [],
    "illustrator": "Ayaka Yoshida",
    "rarity": "uncommon",
    "regulation_mark": "H",
    "variants": [
      {
        "id": "normal",
        "images": {
          "ja": "/images/cards/asia-sv7a/ja/055.webp"
        }
      }
    ],
    "trainer_type": "item",
    "rules_text": {
      "ja": "相手は相手自身の手札を数えたあと、すべてウラにして切り、山札の下にもどす。その後、相手はもどした枚数ぶん、山札を引く。"
    }
  },
  {
    "id": "asia-sv7a-056",
    "set_id": "asia-sv7a",
    "number": "056",
    "category": "trainer",
    "name": {
      "ja": "メガトンブロアー"
    },
    "pokemon": [],
    "illustrator": "Toyste Beach",
    "rarity": "none",
    "regulation_mark": "H",
    "variants": [
      {
        "id": "normal",
        "images": {
          "ja": "/images/cards/asia-sv7a/ja/056.webp"
        }
      }
    ],
    "trainer_type": "item",
    "rules_text": {
      "ja": "相手のポケモン全員についている「ポケモンのどうぐ」と「特殊エネルギー」と、場に出ている「スタジアム」を、すべてトラッシュする。"
    }
  },
  {
    "id": "asia-sv7a-057",
    "set_id": "asia-sv7a",
    "number": "057",
    "category": "trainer",
    "name": {
      "ja": "竜の秘薬"
    },
    "pokemon": [],
    "illustrator": "AYUMI ODASHIMA",
    "rarity": "uncommon",
    "regulation_mark": "H",
    "variants": [
      {
        "id": "normal",
        "images": {
          "ja": "/images/cards/asia-sv7a/ja/057.webp"
        }
      }
    ],
    "trainer_type": "item",
    "rules_text": {
      "ja": "自分のバトル場のポケモンのHPを「60」回復する。"
    }
  },
  {
    "id": "asia-sv7a-058",
    "set_id": "asia-sv7a",
    "number": "058",
    "category": "trainer",
    "name": {
      "ja": "イトケのみ"
    },
    "pokemon": [],
    "illustrator": "Studio Bora Inc.",
    "rarity": "uncommon",
    "regulation_mark": "H",
    "variants": [
      {
        "id": "normal",
        "images": {
          "ja": "/images/cards/asia-sv7a/ja/058.webp"
        }
      }
    ],
    "trainer_type": "tool",
    "rules_text": {
      "ja": "このカードをつけているポケモンが、相手のポケモンからワザのダメージを受けるとき、そのダメージは「-60」され、このカードをトラッシュする。"
    }
  },
  {
    "id": "asia-sv7a-059",
    "set_id": "asia-sv7a",
    "number": "059",
    "category": "trainer",
    "name": {
      "ja": "カウンターゲイン"
    },
    "pokemon": [],
    "illustrator": "Toyste Beach",
    "rarity": "uncommon",
    "regulation_mark": "H",
    "variants": [
      {
        "id": "normal",
        "images": {
          "ja": "/images/cards/asia-sv7a/ja/059.webp"
        }
      }
    ],
    "trainer_type": "tool",
    "rules_text": {
      "ja": "自分のサイドの残り枚数が、相手のサイドの残り枚数より多いなら、このカードをつけているポケモンがワザを使うためのエネルギーは、エネルギー1個ぶん少なくなる。"
    }
  },
  {
    "id": "asia-sv7a-060",
    "set_id": "asia-sv7a",
    "number": "060",
    "category": "trainer",
    "name": {
      "ja": "カキツバタ"
    },
    "pokemon": [],
    "illustrator": "GIDORA",
    "rarity": "uncommon",
    "regulation_mark": "H",
    "variants": [
      {
        "id": "normal",
        "images": {
          "ja": "/images/cards/asia-sv7a/ja/060.webp"
        }
      }
    ],
    "trainer_type": "supporter",
    "rules_text": {
      "ja": "自分の山札を上から7枚見て、その中からポケモンとトレーナーズを1枚ずつ選び、相手に見せて、手札に加える。残りのカードは山札にもどして切る。"
    }
  },
  {
    "id": "asia-sv7a-061",
    "set_id": "asia-sv7a",
    "number": "061",
    "category": "trainer",
    "name": {
      "ja": "サーファー"
    },
    "pokemon": [],
    "illustrator": "Sanosuke Sakuma",
    "rarity": "uncommon",
    "regulation_mark": "H",
    "variants": [
      {
        "id": "normal",
        "images": {
          "ja": "/images/cards/asia-sv7a/ja/061.webp"
        }
      }
    ],
    "trainer_type": "supporter",
    "rules_text": {
      "ja": "自分のバトルポケモンをベンチポケモンと入れ替える。その後、自分の手札が5枚になるように、山札を引く。"
    }
  },
  {
    "id": "asia-sv7a-062",
    "set_id": "asia-sv7a",
    "number": "062",
    "category": "trainer",
    "name": {
      "ja": "ドラセナ"
    },
    "pokemon": [],
    "illustrator": "Hideki Ishikawa",
    "rarity": "common",
    "regulation_mark": "H",
    "variants": [
      {
        "id": "normal",
        "images": {
          "ja": "/images/cards/asia-sv7a/ja/062.webp"
        }
      }
    ],
    "trainer_type": "supporter",
    "rules_text": {
      "ja": "自分の手札をすべて山札にもどして切る。その後、コインを1回投げ、オモテなら8枚、ウラなら3枚、山札を引く。"
    }
  },
  {
    "id": "asia-sv7a-063",
    "set_id": "asia-sv7a",
    "number": "063",
    "category": "trainer",
    "name": {
      "ja": "ルチアのアピール"
    },
    "pokemon": [],
    "illustrator": "En Morikura",
    "rarity": "uncommon",
    "regulation_mark": "H",
    "variants": [
      {
        "id": "normal",
        "images": {
          "ja": "/images/cards/asia-sv7a/ja/063.webp"
        }
      }
    ],
    "trainer_type": "supporter",
    "rules_text": {
      "ja": "相手のベンチのたねポケモンを1匹選び、バトルポケモンと入れ替える。その後、新しく出てきたポケモンをこんらんにする。"
    }
  },
  {
    "id": "asia-sv7a-064",
    "set_id": "asia-sv7a",
    "number": "064",
    "category": "energy",
    "name": {
      "ja": "リッチエネルギー"
    },
    "pokemon": [],
    "illustrator": "5ban Graphics",
    "rarity": "none",
    "regulation_mark": "H",
    "variants": [
      {
        "id": "normal",
        "images": {
          "ja": "/images/cards/asia-sv7a/ja/064.webp"
        }
      }
    ],
    "rules_text": {
      "ja": "このカードは、ポケモンについているかぎり、エネルギー1個ぶんとしてはたらく。\n\nこのカードを手札からポケモンにつけたとき、自分の山札を4枚引く。"
    }
  },
  {
    "id": "asia-sv7a-065",
    "set_id": "asia-sv7a",
    "number": "065",
    "category": "pokemon",
    "name": {
      "ja": "タマタマ"
    },
    "pokemon": [
      "0102"
    ],
    "illustrator": "Yuriko Akase",
    "rarity": "none",
    "regulation_mark": null,
    "variants": [
      {
        "id": "normal",
        "images": {
          "ja": "/images/cards/asia-sv7a/ja/065.webp"
        }
      }
    ],
    "hp": 30,
    "types": [
      "grass"
    ],
    "stage": "basic",
    "attacks": [
      {
        "name": {
          "ja": "そうじゅくしんか"
        },
        "cost": [
          "normal"
        ],
        "damage": "",
        "text": {
          "ja": "このワザは、先攻プレイヤーの最初の番でも使える。このポケモンから進化するカードを、自分の山札から1枚選び、このポケモンにのせて進化させる。そして山札を切る。"
        }
      }
    ],
    "weaknesses": [
      {
        "type": "fire",
        "value": "x2"
      }
    ],
    "retreat_cost": 1,
    "flavor_text": {
      "ja": "タマタマだけに 伝わる テレパシーを 出し合っているので どんなときでも ６匹 集まれる。"
    }
  },
  {
    "id": "asia-sv7a-066",
    "set_id": "asia-sv7a",
    "number": "066",
    "category": "pokemon",
    "name": {
      "ja": "マシェード"
    },
    "pokemon": [
      "0756"
    ],
    "illustrator": "matazo",
    "rarity": "none",
    "regulation_mark": null,
    "variants": [
      {
        "id": "normal",
        "images": {
          "ja": "/images/cards/asia-sv7a/ja/066.webp"
        }
      }
    ],
    "hp": 110,
    "types": [
      "grass"
    ],
    "stage": "stage1",
    "attacks": [
      {
        "name": {
          "ja": "スパイラルラッシュ"
        },
        "cost": [
          "grass",
          "normal"
        ],
        "damage": "60＋",
        "text": {
          "ja": "ウラが出るまでコインを投げ、オモテの数×30ダメージ追加。"
        }
      }
    ],
    "weaknesses": [
      {
        "type": "fire",
        "value": "x2"
      }
    ],
    "retreat_cost": 2,
    "flavor_text": {
      "ja": "点滅する 胞子の 光りで 獲物を おびき寄せて 眠らせる。 指先から 生気を 吸い取る。"
    }
  },
  {
    "id": "asia-sv7a-067",
    "set_id": "asia-sv7a",
    "number": "067",
    "category": "pokemon",
    "name": {
      "ja": "ポワルン たいようのすがた"
    },
    "pokemon": [
      "0351"
    ],
    "illustrator": "Narano",
    "rarity": "none",
    "regulation_mark": null,
    "variants": [
      {
        "id": "normal",
        "images": {
          "ja": "/images/cards/asia-sv7a/ja/067.webp"
        }
      }
    ],
    "hp": 70,
    "types": [
      "fire"
    ],
    "stage": "basic",
    "attacks": [
      {
        "name": {
          "ja": "こがす"
        },
        "cost": [
          "fire"
        ],
        "damage": "",
        "text": {
          "ja": "相手のバトルポケモンをやけどにする。"
        }
      },
      {
        "name": {
          "ja": "サニーアシスト"
        },
        "cost": [
          "fire",
          "normal"
        ],
        "damage": "50",
        "text": {
          "ja": "このポケモンについているエネルギーをすべて、ベンチポケモン1匹につけ替える。"
        }
      }
    ],
    "weaknesses": [
      {
        "type": "water",
        "value": "x2"
      }
    ],
    "retreat_cost": 0,
    "flavor_text": {
      "ja": "晴れた 日の ポワルンの 姿。 ヒーターの前に 置く 実験では この 形に 変化しなかった。"
    }
  },
  {
    "id": "asia-sv7a-068",
    "set_id": "asia-sv7a",
    "number": "068",
    "category": "pokemon",
    "name": {
      "ja": "ハギギシリ"
    },
    "pokemon": [
      "0779"
    ],
    "illustrator": "Mitsuhiro Arita",
    "rarity": "none",
    "regulation_mark": null,
    "variants": [
      {
        "id": "normal",
        "images": {
          "ja": "/images/cards/asia-sv7a/ja/068.webp"
        }
      }
    ],
    "hp": 110,
    "types": [
      "water"
    ],
    "stage": "basic",
    "attacks": [
      {
        "name": {
          "ja": "かじりつく"
        },
        "cost": [
          "water",
          "normal"
        ],
        "damage": "50",
        "text": {
          "ja": "次の相手の番、このワザを受けたポケモンは、にげられない。"
        }
      }
    ],
    "weaknesses": [
      {
        "type": "lightning",
        "value": "x2"
      }
    ],
    "retreat_cost": 1,
    "flavor_text": {
      "ja": "歯ぎしりで 起こる 波紋に 陽の光が 反射するとき まわりの 水は 眩いばかりに きらめく。"
    }
  },
  {
    "id": "asia-sv7a-069",
    "set_id": "asia-sv7a",
    "number": "069",
    "category": "pokemon",
    "name": {
      "ja": "ハルクジラ"
    },
    "pokemon": [
      "0975"
    ],
    "illustrator": "Jerky",
    "rarity": "none",
    "regulation_mark": null,
    "variants": [
      {
        "id": "normal",
        "images": {
          "ja": "/images/cards/asia-sv7a/ja/069.webp"
        }
      }
    ],
    "hp": 180,
    "types": [
      "water"
    ],
    "stage": "stage1",
    "attacks": [
      {
        "name": {
          "ja": "デンジャーマウス"
        },
        "cost": [
          "water",
          "normal",
          "normal",
          "normal"
        ],
        "damage": "150",
        "text": {}
      }
    ],
    "weaknesses": [
      {
        "type": "metal",
        "value": "x2"
      }
    ],
    "retreat_cost": 3,
    "flavor_text": {
      "ja": "氷エネルギーの 集中する 上あごの ツノが 超低温になって 周囲を 凍らせる。"
    }
  },
  {
    "id": "asia-sv7a-070",
    "set_id": "asia-sv7a",
    "number": "070",
    "category": "pokemon",
    "name": {
      "ja": "ラティオス"
    },
    "pokemon": [
      "0381"
    ],
    "illustrator": "OKACHEKE",
    "rarity": "none",
    "regulation_mark": null,
    "variants": [
      {
        "id": "normal",
        "images": {
          "ja": "/images/cards/asia-sv7a/ja/070.webp"
        }
      }
    ],
    "hp": 120,
    "types": [
      "psychic"
    ],
    "stage": "basic",
    "attacks": [
      {
        "name": {
          "ja": "ちょくげきひこう"
        },
        "cost": [
          "psychic",
          "normal"
        ],
        "damage": "",
        "text": {
          "ja": "相手のポケモン1匹に、50ダメージ。［ベンチは弱点・抵抗力を計算しない。］"
        }
      },
      {
        "name": {
          "ja": "ジェットヘッド"
        },
        "cost": [
          "psychic",
          "psychic",
          "normal"
        ],
        "damage": "110",
        "text": {}
      }
    ],
    "weaknesses": [
      {
        "type": "dark",
        "value": "x2"
      }
    ],
    "resistances": [
      {
        "type": "fighting",
        "value": "－30"
      }
    ],
    "retreat_cost": 2,
    "flavor_text": {
      "ja": "高い 知能を 持つ ポケモン。 腕を 折りたたんで 飛べば ジェット機を 追い越す スピードだ。"
    }
  },
  {
    "id": "asia-sv7a-071",
    "set_id": "asia-sv7a",
    "number": "071",
    "category": "pokemon",
    "name": {
      "ja": "ビブラーバ"
    },
    "pokemon": [
      "0329"
    ],
    "illustrator": "toriyufu",
    "rarity": "none",
    "regulation_mark": null,
    "variants": [
      {
        "id": "normal",
        "images": {
          "ja": "/images/cards/asia-sv7a/ja/071.webp"
        }
      }
    ],
    "hp": 90,
    "types": [
      "fighting"
    ],
    "stage": "stage1",
    "attacks": [
      {
        "name": {
          "ja": "いやなおと"
        },
        "cost": [
          "normal"
        ],
        "damage": "",
        "text": {
          "ja": "次の自分の番、このワザを受けたポケモンが受けるワザのダメージは「+50」される。"
        }
      },
      {
        "name": {
          "ja": "カッターウインド"
        },
        "cost": [
          "fighting",
          "normal"
        ],
        "damage": "50",
        "text": {}
      }
    ],
    "weaknesses": [
      {
        "type": "grass",
        "value": "x2"
      }
    ],
    "retreat_cost": 1,
    "flavor_text": {
      "ja": "翅を 激しく 振動させて 超音波を 発生。 気絶した 獲物を 消化液で 溶かす。"
    }
  },
  {
    "id": "asia-sv7a-072",
    "set_id": "asia-sv7a",
    "number": "072",
    "category": "pokemon",
    "name": {
      "ja": "タタッコ"
    },
    "pokemon": [
      "0852"
    ],
    "illustrator": "USGMEN",
    "rarity": "none",
    "regulation_mark": null,
    "variants": [
      {
        "id": "normal",
        "images": {
          "ja": "/images/cards/asia-sv7a/ja/072.webp"
        }
      }
    ],
    "hp": 70,
    "types": [
      "fighting"
    ],
    "stage": "basic",
    "attacks": [
      {
        "name": {
          "ja": "ちょっとつっこむ"
        },
        "cost": [
          "fighting"
        ],
        "damage": "30",
        "text": {
          "ja": "このポケモンにも10ダメージ。"
        }
      }
    ],
    "weaknesses": [
      {
        "type": "psychic",
        "value": "x2"
      }
    ],
    "retreat_cost": 2,
    "flavor_text": {
      "ja": "餌を 求め 地上に 上がる。 好奇心旺盛で 目にしたものは とりあえず 触手で 殴る。"
    }
  },
  {
    "id": "asia-sv7a-073",
    "set_id": "asia-sv7a",
    "number": "073",
    "category": "pokemon",
    "name": {
      "ja": "エアームド"
    },
    "pokemon": [
      "0227"
    ],
    "illustrator": "Takumi Wada",
    "rarity": "none",
    "regulation_mark": null,
    "variants": [
      {
        "id": "normal",
        "images": {
          "ja": "/images/cards/asia-sv7a/ja/073.webp"
        }
      }
    ],
    "hp": 110,
    "types": [
      "metal"
    ],
    "stage": "basic",
    "attacks": [
      {
        "name": {
          "ja": "はがねのつばさ"
        },
        "cost": [
          "metal",
          "normal"
        ],
        "damage": "50",
        "text": {
          "ja": "次の相手の番、このポケモンが受けるワザのダメージは「-30」される。"
        }
      }
    ],
    "weaknesses": [
      {
        "type": "lightning",
        "value": "x2"
      }
    ],
    "resistances": [
      {
        "type": "fighting",
        "value": "－30"
      }
    ],
    "retreat_cost": 1,
    "flavor_text": {
      "ja": "抜け落ちた 羽根は 薄く 鋭いので 刀として 使われていたことも あったらしい。"
    }
  },
  {
    "id": "asia-sv7a-074",
    "set_id": "asia-sv7a",
    "number": "074",
    "category": "pokemon",
    "name": {
      "ja": "アップリュー"
    },
    "pokemon": [
      "0841"
    ],
    "illustrator": "Uninori",
    "rarity": "none",
    "regulation_mark": null,
    "variants": [
      {
        "id": "normal",
        "images": {
          "ja": "/images/cards/asia-sv7a/ja/074.webp"
        }
      }
    ],
    "hp": 80,
    "types": [
      "dragon"
    ],
    "stage": "stage1",
    "attacks": [
      {
        "name": {
          "ja": "サワースピット"
        },
        "cost": [
          "normal"
        ],
        "damage": "20×",
        "text": {
          "ja": "相手のバトルポケモンにのっているダメカンの数×20ダメージ。"
        }
      },
      {
        "name": {
          "ja": "スピードひこう"
        },
        "cost": [
          "grass",
          "fire"
        ],
        "damage": "70",
        "text": {}
      }
    ],
    "retreat_cost": 1,
    "flavor_text": {
      "ja": "体液で りんごを 補修する。 歴戦の 強者の りんごは 全体的に 粘土色。"
    }
  },
  {
    "id": "asia-sv7a-075",
    "set_id": "asia-sv7a",
    "number": "075",
    "category": "pokemon",
    "name": {
      "ja": "タルップル"
    },
    "pokemon": [
      "0842"
    ],
    "illustrator": "MINAMINAMI Take",
    "rarity": "none",
    "regulation_mark": null,
    "variants": [
      {
        "id": "normal",
        "images": {
          "ja": "/images/cards/asia-sv7a/ja/075.webp"
        }
      }
    ],
    "hp": 90,
    "types": [
      "dragon"
    ],
    "stage": "stage1",
    "attacks": [
      {
        "name": {
          "ja": "スイートメルト"
        },
        "cost": [
          "normal",
          "normal"
        ],
        "damage": "50",
        "text": {
          "ja": "次の相手の番、このワザを受けたポケモンは、ワザが使えない。"
        }
      },
      {
        "name": {
          "ja": "ワイルドタックル"
        },
        "cost": [
          "grass",
          "fire"
        ],
        "damage": "130",
        "text": {
          "ja": "このポケモンにも20ダメージ。"
        }
      }
    ],
    "retreat_cost": 3,
    "flavor_text": {
      "ja": "背中の 甘い蜜を 舐め取りに やって来る グルトンに ベトベトの 蜜を 吐きかけ 退ける。"
    }
  },
  {
    "id": "asia-sv7a-076",
    "set_id": "asia-sv7a",
    "number": "076",
    "category": "pokemon",
    "name": {
      "ja": "ウォーグル"
    },
    "pokemon": [
      "0628"
    ],
    "illustrator": "Gapao",
    "rarity": "none",
    "regulation_mark": null,
    "variants": [
      {
        "id": "normal",
        "images": {
          "ja": "/images/cards/asia-sv7a/ja/076.webp"
        }
      }
    ],
    "hp": 130,
    "types": [
      "normal"
    ],
    "stage": "stage1",
    "attacks": [
      {
        "name": {
          "ja": "ひきずりだす"
        },
        "cost": [
          "normal",
          "normal"
        ],
        "damage": "",
        "text": {
          "ja": "相手のベンチポケモンを1匹選び、バトルポケモンと入れ替える。その後、新しく出てきたポケモンに40ダメージ。"
        }
      },
      {
        "name": {
          "ja": "ブラストウインド"
        },
        "cost": [
          "normal",
          "normal",
          "normal"
        ],
        "damage": "120",
        "text": {}
      }
    ],
    "weaknesses": [
      {
        "type": "lightning",
        "value": "x2"
      }
    ],
    "resistances": [
      {
        "type": "fighting",
        "value": "－30"
      }
    ],
    "retreat_cost": 1,
    "flavor_text": {
      "ja": "仲間の ためなら どれだけ 傷つこうとも 戦いを やめない 勇敢な 大空の 戦士。"
    }
  },
  {
    "id": "asia-sv7a-077",
    "set_id": "asia-sv7a",
    "number": "077",
    "category": "pokemon",
    "name": {
      "ja": "ブラックキュレムex"
    },
    "pokemon": [
      "0646"
    ],
    "illustrator": "N-DESIGN Inc.",
    "rarity": "none",
    "regulation_mark": null,
    "variants": [
      {
        "id": "normal",
        "images": {
          "ja": "/images/cards/asia-sv7a/ja/077.webp"
        }
      }
    ],
    "hp": 230,
    "types": [
      "water"
    ],
    "stage": "basic",
    "rule_box": "EX",
    "attacks": [
      {
        "name": {
          "ja": "アイスエイジ"
        },
        "cost": [
          "normal",
          "normal",
          "normal"
        ],
        "damage": "90",
        "text": {
          "ja": "相手のバトルポケモンがポケモンなら、そのポケモンをマヒにする。"
        }
      },
      {
        "name": {
          "ja": "ブラックフロスト"
        },
        "cost": [
          "water",
          "water",
          "normal",
          "normal"
        ],
        "damage": "250",
        "text": {
          "ja": "このポケモンにも30ダメージ。"
        }
      }
    ],
    "weaknesses": [
      {
        "type": "metal",
        "value": "x2"
      }
    ],
    "retreat_cost": 3
  },
  {
    "id": "asia-sv7a-078",
    "set_id": "asia-sv7a",
    "number": "078",
    "category": "pokemon",
    "name": {
      "ja": "ラティアスex"
    },
    "pokemon": [
      "0380"
    ],
    "illustrator": "takuyoa",
    "rarity": "none",
    "regulation_mark": null,
    "variants": [
      {
        "id": "normal",
        "images": {
          "ja": "/images/cards/asia-sv7a/ja/078.webp"
        }
      }
    ],
    "hp": 210,
    "types": [
      "psychic"
    ],
    "stage": "basic",
    "rule_box": "EX",
    "attacks": [
      {
        "name": {
          "ja": "むげんのやいば"
        },
        "cost": [
          "psychic",
          "psychic",
          "normal"
        ],
        "damage": "200",
        "text": {
          "ja": "次の自分の番、このポケモンはワザが使えない。"
        }
      }
    ],
    "weaknesses": [
      {
        "type": "dark",
        "value": "x2"
      }
    ],
    "resistances": [
      {
        "type": "fighting",
        "value": "－30"
      }
    ],
    "retreat_cost": 2
  },
  {
    "id": "asia-sv7a-079",
    "set_id": "asia-sv7a",
    "number": "079",
    "category": "pokemon",
    "name": {
      "ja": "フライゴンex"
    },
    "pokemon": [],
    "illustrator": "5ban Graphics",
    "rarity": "none",
    "regulation_mark": null,
    "variants": [
      {
        "id": "normal",
        "images": {
          "ja": "/images/cards/asia-sv7a/ja/079.webp"
        }
      }
    ],
    "hp": 310,
    "types": [
      "fighting"
    ],
    "stage": "stage2",
    "rule_box": "EX",
    "attacks": [
      {
        "name": {
          "ja": "ストームバック"
        },
        "cost": [
          "fighting"
        ],
        "damage": "130",
        "text": {
          "ja": "のぞむなら、このポケモンをベンチポケモンと入れ替える。"
        }
      },
      {
        "name": {
          "ja": "ペリドットソニック"
        },
        "cost": [
          "water",
          "fighting",
          "metal"
        ],
        "damage": "",
        "text": {
          "ja": "相手の「ポケモンex・V」全員に、それぞれ100ダメージ。このワザのダメージは弱点・抵抗力を計算しない。"
        }
      }
    ],
    "weaknesses": [
      {
        "type": "grass",
        "value": "x2"
      }
    ],
    "retreat_cost": 1
  },
  {
    "id": "asia-sv7a-080",
    "set_id": "asia-sv7a",
    "number": "080",
    "category": "pokemon",
    "name": {
      "ja": "ブリジュラスex"
    },
    "pokemon": [
      "1018"
    ],
    "illustrator": "5ban Graphics",
    "rarity": "none",
    "regulation_mark": null,
    "variants": [
      {
        "id": "normal",
        "images": {
          "ja": "/images/cards/asia-sv7a/ja/080.webp"
        }
      }
    ],
    "hp": 300,
    "types": [
      "metal"
    ],
    "stage": "stage1",
    "rule_box": "EX",
    "attacks": [
      {
        "name": {
          "ja": "メタルディフェンダー"
        },
        "cost": [
          "metal",
          "metal",
          "metal"
        ],
        "damage": "220",
        "text": {
          "ja": "次の相手の番、このポケモンの弱点は、すべてなくなる。"
        }
      }
    ],
    "weaknesses": [
      {
        "type": "fire",
        "value": "x2"
      }
    ],
    "resistances": [
      {
        "type": "grass",
        "value": "－30"
      }
    ],
    "retreat_cost": 2
  },
  {
    "id": "asia-sv7a-081",
    "set_id": "asia-sv7a",
    "number": "081",
    "category": "pokemon",
    "name": {
      "ja": "アローラ ナッシーex"
    },
    "pokemon": [
      "0103"
    ],
    "illustrator": "aky CG Works",
    "rarity": "none",
    "regulation_mark": null,
    "variants": [
      {
        "id": "normal",
        "images": {
          "ja": "/images/cards/asia-sv7a/ja/081.webp"
        }
      }
    ],
    "hp": 300,
    "types": [
      "dragon"
    ],
    "stage": "stage1",
    "rule_box": "EX",
    "attacks": [
      {
        "name": {
          "ja": "トロピカルフィーバー"
        },
        "cost": [
          "grass",
          "water"
        ],
        "damage": "150",
        "text": {
          "ja": "自分の手札から基本エネルギーを好きなだけ選び、自分のポケモンに好きなようにつける。"
        }
      },
      {
        "name": {
          "ja": "ブンブンスフェーン"
        },
        "cost": [
          "grass",
          "water",
          "fighting"
        ],
        "damage": "",
        "text": {
          "ja": "コインを1回投げオモテなら、相手のバトル場のたねポケモンをきぜつさせる。ウラなら、相手のベンチのたねポケモンを1匹選び、きぜつさせる。"
        }
      }
    ],
    "retreat_cost": 3
  },
  {
    "id": "asia-sv7a-082",
    "set_id": "asia-sv7a",
    "number": "082",
    "category": "pokemon",
    "name": {
      "ja": "モトトカゲex"
    },
    "pokemon": [],
    "illustrator": "5ban Graphics",
    "rarity": "none",
    "regulation_mark": null,
    "variants": [
      {
        "id": "normal",
        "images": {
          "ja": "/images/cards/asia-sv7a/ja/082.webp"
        }
      }
    ],
    "hp": 210,
    "types": [
      "normal"
    ],
    "stage": "basic",
    "rule_box": "EX",
    "attacks": [
      {
        "name": {
          "ja": "ブレイクスルー"
        },
        "cost": [
          "normal",
          "normal",
          "normal"
        ],
        "damage": "130",
        "text": {
          "ja": "相手のベンチポケモン1匹にも、30ダメージ。［ベンチは弱点・抵抗力を計算しない。］"
        }
      },
      {
        "name": {
          "ja": "ジルコンロード"
        },
        "cost": [
          "grass",
          "fire",
          "psychic"
        ],
        "damage": "180",
        "text": {
          "ja": "のぞむなら、自分の山札を5枚引く。"
        }
      }
    ],
    "weaknesses": [
      {
        "type": "fighting",
        "value": "x2"
      }
    ],
    "retreat_cost": 1
  },
  {
    "id": "asia-sv7a-083",
    "set_id": "asia-sv7a",
    "number": "083",
    "category": "trainer",
    "name": {
      "ja": "カキツバタ"
    },
    "pokemon": [],
    "illustrator": "GIDORA",
    "rarity": "none",
    "regulation_mark": null,
    "variants": [
      {
        "id": "normal",
        "images": {
          "ja": "/images/cards/asia-sv7a/ja/083.webp"
        }
      }
    ],
    "trainer_type": "supporter",
    "rules_text": {
      "ja": "自分の山札を上から7枚見て、その中からポケモンとトレーナーズを1枚ずつ選び、相手に見せて、手札に加える。残りのカードは山札にもどして切る。"
    }
  },
  {
    "id": "asia-sv7a-084",
    "set_id": "asia-sv7a",
    "number": "084",
    "category": "trainer",
    "name": {
      "ja": "サーファー"
    },
    "pokemon": [],
    "illustrator": "Sanosuke Sakuma",
    "rarity": "none",
    "regulation_mark": null,
    "variants": [
      {
        "id": "normal",
        "images": {
          "ja": "/images/cards/asia-sv7a/ja/084.webp"
        }
      }
    ],
    "trainer_type": "supporter",
    "rules_text": {
      "ja": "自分のバトルポケモンをベンチポケモンと入れ替える。その後、自分の手札が5枚になるように、山札を引く。"
    }
  },
  {
    "id": "asia-sv7a-085",
    "set_id": "asia-sv7a",
    "number": "085",
    "category": "trainer",
    "name": {
      "ja": "ドラセナ"
    },
    "pokemon": [],
    "illustrator": "Hideki Ishikawa",
    "rarity": "none",
    "regulation_mark": null,
    "variants": [
      {
        "id": "normal",
        "images": {
          "ja": "/images/cards/asia-sv7a/ja/085.webp"
        }
      }
    ],
    "trainer_type": "supporter",
    "rules_text": {
      "ja": "自分の手札をすべて山札にもどして切る。その後、コインを1回投げ、オモテなら8枚、ウラなら3枚、山札を引く。"
    }
  },
  {
    "id": "asia-sv7a-086",
    "set_id": "asia-sv7a",
    "number": "086",
    "category": "trainer",
    "name": {
      "ja": "ルチアのアピール"
    },
    "pokemon": [],
    "illustrator": "En Morikura",
    "rarity": "none",
    "regulation_mark": null,
    "variants": [
      {
        "id": "normal",
        "images": {
          "ja": "/images/cards/asia-sv7a/ja/086.webp"
        }
      }
    ],
    "trainer_type": "supporter",
    "rules_text": {
      "ja": "相手のベンチのたねポケモンを1匹選び、バトルポケモンと入れ替える。その後、新しく出てきたポケモンをこんらんにする。"
    }
  },
  {
    "id": "asia-sv7a-087",
    "set_id": "asia-sv7a",
    "number": "087",
    "category": "pokemon",
    "name": {
      "ja": "ラティアスex"
    },
    "pokemon": [
      "0380"
    ],
    "illustrator": "OKACHEKE",
    "rarity": "none",
    "regulation_mark": null,
    "variants": [
      {
        "id": "normal",
        "images": {
          "ja": "/images/cards/asia-sv7a/ja/087.webp"
        }
      }
    ],
    "hp": 210,
    "types": [
      "psychic"
    ],
    "stage": "basic",
    "rule_box": "EX",
    "attacks": [
      {
        "name": {
          "ja": "むげんのやいば"
        },
        "cost": [
          "psychic",
          "psychic",
          "normal"
        ],
        "damage": "200",
        "text": {
          "ja": "次の自分の番、このポケモンはワザが使えない。"
        }
      }
    ],
    "weaknesses": [
      {
        "type": "dark",
        "value": "x2"
      }
    ],
    "resistances": [
      {
        "type": "fighting",
        "value": "－30"
      }
    ],
    "retreat_cost": 2
  },
  {
    "id": "asia-sv7a-088",
    "set_id": "asia-sv7a",
    "number": "088",
    "category": "pokemon",
    "name": {
      "ja": "ブリジュラスex"
    },
    "pokemon": [
      "1018"
    ],
    "illustrator": "Shinya Mizuno",
    "rarity": "none",
    "regulation_mark": null,
    "variants": [
      {
        "id": "normal",
        "images": {
          "ja": "/images/cards/asia-sv7a/ja/088.webp"
        }
      }
    ],
    "hp": 300,
    "types": [
      "metal"
    ],
    "stage": "stage1",
    "rule_box": "EX",
    "attacks": [
      {
        "name": {
          "ja": "メタルディフェンダー"
        },
        "cost": [
          "metal",
          "metal",
          "metal"
        ],
        "damage": "220",
        "text": {
          "ja": "次の相手の番、このポケモンの弱点は、すべてなくなる。"
        }
      }
    ],
    "weaknesses": [
      {
        "type": "fire",
        "value": "x2"
      }
    ],
    "resistances": [
      {
        "type": "grass",
        "value": "－30"
      }
    ],
    "retreat_cost": 2
  },
  {
    "id": "asia-sv7a-089",
    "set_id": "asia-sv7a",
    "number": "089",
    "category": "pokemon",
    "name": {
      "ja": "アローラ ナッシーex"
    },
    "pokemon": [
      "0103"
    ],
    "illustrator": "Yuriko Akase",
    "rarity": "none",
    "regulation_mark": null,
    "variants": [
      {
        "id": "normal",
        "images": {
          "ja": "/images/cards/asia-sv7a/ja/089.webp"
        }
      }
    ],
    "hp": 300,
    "types": [
      "dragon"
    ],
    "stage": "stage1",
    "rule_box": "EX",
    "attacks": [
      {
        "name": {
          "ja": "トロピカルフィーバー"
        },
        "cost": [
          "grass",
          "water"
        ],
        "damage": "150",
        "text": {
          "ja": "自分の手札から基本エネルギーを好きなだけ選び、自分のポケモンに好きなようにつける。"
        }
      },
      {
        "name": {
          "ja": "ブンブンスフェーン"
        },
        "cost": [
          "grass",
          "water",
          "fighting"
        ],
        "damage": "",
        "text": {
          "ja": "コインを1回投げオモテなら、相手のバトル場のたねポケモンをきぜつさせる。ウラなら、相手のベンチのたねポケモンを1匹選び、きぜつさせる。"
        }
      }
    ],
    "retreat_cost": 3
  },
  {
    "id": "asia-sv7a-090",
    "set_id": "asia-sv7a",
    "number": "090",
    "category": "trainer",
    "name": {
      "ja": "カキツバタ"
    },
    "pokemon": [],
    "illustrator": "DOM",
    "rarity": "none",
    "regulation_mark": null,
    "variants": [
      {
        "id": "normal",
        "images": {
          "ja": "/images/cards/asia-sv7a/ja/090.webp"
        }
      }
    ],
    "trainer_type": "supporter",
    "rules_text": {
      "ja": "自分の山札を上から7枚見て、その中からポケモンとトレーナーズを1枚ずつ選び、相手に見せて、手札に加える。残りのカードは山札にもどして切る。"
    }
  },
  {
    "id": "asia-sv7a-091",
    "set_id": "asia-sv7a",
    "number": "091",
    "category": "trainer",
    "name": {
      "ja": "ルチアのアピール"
    },
    "pokemon": [],
    "illustrator": "Nobusawa/Mochipuyo",
    "rarity": "none",
    "regulation_mark": null,
    "variants": [
      {
        "id": "normal",
        "images": {
          "ja": "/images/cards/asia-sv7a/ja/091.webp"
        }
      }
    ],
    "trainer_type": "supporter",
    "rules_text": {
      "ja": "相手のベンチのたねポケモンを1匹選び、バトルポケモンと入れ替える。その後、新しく出てきたポケモンをこんらんにする。"
    }
  },
  {
    "id": "asia-sv7a-092",
    "set_id": "asia-sv7a",
    "number": "092",
    "category": "pokemon",
    "name": {
      "ja": "アローラ ナッシーex"
    },
    "pokemon": [
      "0103"
    ],
    "illustrator": "aky CG Works",
    "rarity": "none",
    "regulation_mark": null,
    "variants": [
      {
        "id": "normal",
        "images": {
          "ja": "/images/cards/asia-sv7a/ja/092.webp"
        }
      }
    ],
    "hp": 300,
    "types": [
      "dragon"
    ],
    "stage": "stage1",
    "rule_box": "EX",
    "attacks": [
      {
        "name": {
          "ja": "トロピカルフィーバー"
        },
        "cost": [
          "grass",
          "water"
        ],
        "damage": "150",
        "text": {
          "ja": "自分の手札から基本エネルギーを好きなだけ選び、自分のポケモンに好きなようにつける。"
        }
      },
      {
        "name": {
          "ja": "ブンブンスフェーン"
        },
        "cost": [
          "grass",
          "water",
          "fighting"
        ],
        "damage": "",
        "text": {
          "ja": "コインを1回投げオモテなら、相手のバトル場のたねポケモンをきぜつさせる。ウラなら、相手のベンチのたねポケモンを1匹選び、きぜつさせる。"
        }
      }
    ],
    "retreat_cost": 3
  },
  {
    "id": "asia-sv7a-093",
    "set_id": "asia-sv7a",
    "number": "093",
    "category": "trainer",
    "name": {
      "ja": "カウンターゲイン"
    },
    "pokemon": [],
    "illustrator": "Toyste Beach",
    "rarity": "none",
    "regulation_mark": null,
    "variants": [
      {
        "id": "normal",
        "images": {
          "ja": "/images/cards/asia-sv7a/ja/093.webp"
        }
      }
    ],
    "trainer_type": "tool",
    "rules_text": {
      "ja": "自分のサイドの残り枚数が、相手のサイドの残り枚数より多いなら、このカードをつけているポケモンがワザを使うためのエネルギーは、エネルギー1個ぶん少なくなる。"
    }
  },
  {
    "id": "asia-sv7a-094",
    "set_id": "asia-sv7a",
    "number": "094",
    "category": "energy",
    "name": {
      "ja": "ジェットエネルギー"
    },
    "pokemon": [],
    "illustrator": null,
    "rarity": "none",
    "regulation_mark": null,
    "variants": [
      {
        "id": "normal",
        "images": {
          "ja": "/images/cards/asia-sv7a/ja/094.webp"
        }
      }
    ],
    "rules_text": {
      "ja": "このカードは、ポケモンについているかぎり、エネルギー1個ぶんとしてはたらく。\n\nこのカードを手札からベンチポケモンにつけたとき、このカードをつけたポケモンを、バトルポケモンと入れ替える。"
    }
  }
]
