[
  {
    "id": "asia-e3-001",
    "set_id": "asia-e3",
    "number": "001",
    "category": "pokemon",
    "name": {
      "ja": "奇妙な"
    },
    "pokemon": [
      "奇妙な"
    ],
    "illustrator": null,
    "rarity": "common",
    "regulation_mark": null,
    "variants": [
      {
        "id": "normal",
        "images": {
          "ja": ""
        }
      },
      {
        "id": "stamped",
        "images": {
          "ja": ""
        }
      }
    ],
    "hp": 50,
    "types": [
      "grass"
    ],
    "stage": "basic",
    "attacks": [
      {
        "name": {
          "ja": "スタン胞子"
        },
        "cost": [
          "grass"
        ],
        "damage": "",
        "text": {
          "ja": "コインをひっくり返します。頭の場合、防御ポケモンは麻痺しています。"
        }
      },
      {
        "name": {
          "ja": "ラム"
        },
        "cost": [
          "normal",
          "normal"
        ],
        "damage": "20",
        "text": {}
      }
    ],
    "retreat_cost": 1
  },
  {
    "id": "asia-e3-002",
    "set_id": "asia-e3",
    "number": "002",
    "category": "pokemon",
    "name": {
      "ja": "暗闇"
    },
    "pokemon": [
      "暗闇"
    ],
    "illustrator": null,
    "rarity": "common",
    "regulation_mark": null,
    "variants": [
      {
        "id": "normal",
        "images": {
          "ja": ""
        }
      },
      {
        "id": "stamped",
        "images": {
          "ja": ""
        }
      }
    ],
    "hp": 70,
    "types": [
      "grass"
    ],
    "stage": "stage1",
    "attacks": [
      {
        "name": {
          "ja": "眠り眠り"
        },
        "cost": [
          "normal",
          "normal"
        ],
        "damage": "20",
        "text": {
          "ja": "防御するポケモンと暗闇の両方が眠っています（ダメージを与えた後）。"
        }
      }
    ],
    "retreat_cost": 2
  },
  {
    "id": "asia-e3-003",
    "set_id": "asia-e3",
    "number": "003",
    "category": "pokemon",
    "name": {
      "ja": "vileplume"
    },
    "pokemon": [
      "vileplume"
    ],
    "illustrator": null,
    "rarity": "rare",
    "regulation_mark": null,
    "variants": [
      {
        "id": "normal",
        "images": {
          "ja": ""
        }
      },
      {
        "id": "stamped",
        "images": {
          "ja": ""
        }
      }
    ],
    "hp": 100,
    "types": [
      "grass"
    ],
    "stage": "stage2",
    "attacks": [
      {
        "name": {
          "ja": "毒の香り"
        },
        "cost": [
          "grass"
        ],
        "damage": "",
        "text": {
          "ja": "コインをひっくり返します。頭の場合、防御するポケモンは毒され、混乱しています。尾の場合、防御するポケモンは毒され、眠っています。"
        }
      },
      {
        "name": {
          "ja": "中毒性の花粉"
        },
        "cost": [
          "normal",
          "normal",
          "normal"
        ],
        "damage": "40",
        "text": {
          "ja": "コインをひっくり返します。頭の場合、対戦相手は次のターン中にサポーターカードをプレイできません。"
        }
      }
    ],
    "retreat_cost": 2
  },
  {
    "id": "asia-e3-004",
    "set_id": "asia-e3",
    "number": "004",
    "category": "pokemon",
    "name": {
      "ja": "vileplume"
    },
    "pokemon": [
      "vileplume"
    ],
    "illustrator": null,
    "rarity": "holo_rare",
    "regulation_mark": null,
    "variants": [
      {
        "id": "holo",
        "images": {
          "ja": ""
        }
      },
      {
        "id": "stamped",
        "images": {
          "ja": ""
        }
      }
    ],
    "hp": 100,
    "types": [
      "grass"
    ],
    "stage": "stage2",
    "attacks": [
      {
        "name": {
          "ja": "毒の香り"
        },
        "cost": [
          "grass"
        ],
        "damage": "",
        "text": {
          "ja": "コインをひっくり返します。頭の場合、防御するポケモンは毒され、混乱しています。尾の場合、防御するポケモンは毒され、眠っています。"
        }
      },
      {
        "name": {
          "ja": "中毒性の花粉"
        },
        "cost": [
          "normal",
          "normal",
          "normal"
        ],
        "damage": "40",
        "text": {
          "ja": "コインをひっくり返します。頭の場合、対戦相手は次のターン中にサポーターカードをプレイできません。"
        }
      }
    ],
    "retreat_cost": 2
  },
  {
    "id": "asia-e3-005",
    "set_id": "asia-e3",
    "number": "005",
    "category": "pokemon",
    "name": {
      "ja": "パラ"
    },
    "pokemon": [
      "パラ"
    ],
    "illustrator": null,
    "rarity": "common",
    "regulation_mark": null,
    "variants": [
      {
        "id": "normal",
        "images": {
          "ja": ""
        }
      },
      {
        "id": "stamped",
        "images": {
          "ja": ""
        }
      }
    ],
    "hp": 50,
    "types": [
      "grass"
    ],
    "stage": "basic",
    "attacks": [
      {
        "name": {
          "ja": "胞子"
        },
        "cost": [
          "normal"
        ],
        "damage": "",
        "text": {
          "ja": "防御ポケモンは今眠っています。"
        }
      },
      {
        "name": {
          "ja": "胞子の進化"
        },
        "cost": [
          "grass",
          "normal"
        ],
        "damage": "",
        "text": {
          "ja": "パラから進化するカードをデッキで検索してください。パラに添付します。これは進化するパラとしてカウントされます。その後、デッキをシャッフルします。"
        }
      }
    ],
    "retreat_cost": 1
  },
  {
    "id": "asia-e3-006",
    "set_id": "asia-e3",
    "number": "006",
    "category": "pokemon",
    "name": {
      "ja": "パラセクト"
    },
    "pokemon": [
      "パラセクト"
    ],
    "illustrator": null,
    "rarity": "uncommon",
    "regulation_mark": null,
    "variants": [
      {
        "id": "normal",
        "images": {
          "ja": ""
        }
      },
      {
        "id": "stamped",
        "images": {
          "ja": ""
        }
      }
    ],
    "hp": 70,
    "types": [
      "grass"
    ],
    "stage": "stage1",
    "attacks": [
      {
        "name": {
          "ja": "スリープインデューサー"
        },
        "cost": [
          "grass"
        ],
        "damage": "",
        "text": {
          "ja": "対戦相手のベンチ付きポケモンの1つを選択し、防御ポケモンをそれで切り替えます。新しい防御ポケモンは今眠っています。"
        }
      },
      {
        "name": {
          "ja": "歓喜"
        },
        "cost": [
          "normal",
          "normal"
        ],
        "damage": "20",
        "text": {
          "ja": "コインをひっくり返します。頭の場合、防御するポケモンは今眠っています。テールの場合、ParaSectから2つのダメージカウンターを削除します。"
        }
      }
    ],
    "retreat_cost": 1
  },
  {
    "id": "asia-e3-007",
    "set_id": "asia-e3",
    "number": "007",
    "category": "pokemon",
    "name": {
      "ja": "ベルスプラウト"
    },
    "pokemon": [
      "ベルスプラウト"
    ],
    "illustrator": null,
    "rarity": "common",
    "regulation_mark": null,
    "variants": [
      {
        "id": "normal",
        "images": {
          "ja": ""
        }
      },
      {
        "id": "stamped",
        "images": {
          "ja": ""
        }
      }
    ],
    "hp": 40,
    "types": [
      "grass"
    ],
    "stage": "basic",
    "attacks": [
      {
        "name": {
          "ja": "毒vine"
        },
        "cost": [
          "normal"
        ],
        "damage": "",
        "text": {
          "ja": "コインをひっくり返します。頭の場合、防御ポケモンは現在毒されています。"
        }
      },
      {
        "name": {
          "ja": "鋭い葉"
        },
        "cost": [
          "grass"
        ],
        "damage": "",
        "text": {
          "ja": "コインをひっくり返します。頭の場合、この攻撃は10ダメージに加えて10ダメージを与えます。"
        }
      }
    ],
    "retreat_cost": 1
  },
  {
    "id": "asia-e3-008",
    "set_id": "asia-e3",
    "number": "008",
    "category": "pokemon",
    "name": {
      "ja": "ベルスプラウト"
    },
    "pokemon": [
      "ベルスプラウト"
    ],
    "illustrator": null,
    "rarity": "common",
    "regulation_mark": null,
    "variants": [
      {
        "id": "normal",
        "images": {
          "ja": ""
        }
      },
      {
        "id": "stamped",
        "images": {
          "ja": ""
        }
      }
    ],
    "hp": 50,
    "types": [
      "grass"
    ],
    "stage": "basic",
    "attacks": [
      {
        "name": {
          "ja": "ブロット"
        },
        "cost": [
          "grass",
          "normal"
        ],
        "damage": "20",
        "text": {
          "ja": "Bellsproutから1つのダメージカウンターを取り外します。"
        }
      }
    ],
    "retreat_cost": 1
  },
  {
    "id": "asia-e3-009",
    "set_id": "asia-e3",
    "number": "009",
    "category": "pokemon",
    "name": {
      "ja": "weepinbell"
    },
    "pokemon": [
      "weepinbell"
    ],
    "illustrator": null,
    "rarity": "common",
    "regulation_mark": null,
    "variants": [
      {
        "id": "normal",
        "images": {
          "ja": ""
        }
      },
      {
        "id": "stamped",
        "images": {
          "ja": ""
        }
      }
    ],
    "hp": 70,
    "types": [
      "grass"
    ],
    "stage": "stage1",
    "attacks": [
      {
        "name": {
          "ja": "成長"
        },
        "cost": [
          "normal"
        ],
        "damage": "",
        "text": {
          "ja": "あなたの手からweepinbellに最大2匹の草のエネルギーカードを取り付けます。"
        }
      },
      {
        "name": {
          "ja": "ダブルレザーの葉"
        },
        "cost": [
          "grass",
          "normal"
        ],
        "damage": "",
        "text": {
          "ja": "2つのコインをフリップします。この攻撃は、ヘッド数の30回のダメージ時間を実行します。"
        }
      }
    ],
    "retreat_cost": 1
  },
  {
    "id": "asia-e3-010",
    "set_id": "asia-e3",
    "number": "010",
    "category": "pokemon",
    "name": {
      "ja": "Victreebel"
    },
    "pokemon": [
      "Victreebel"
    ],
    "illustrator": null,
    "rarity": "rare",
    "regulation_mark": null,
    "variants": [
      {
        "id": "normal",
        "images": {
          "ja": ""
        }
      },
      {
        "id": "stamped",
        "images": {
          "ja": ""
        }
      }
    ],
    "hp": 90,
    "types": [
      "grass"
    ],
    "stage": "stage2",
    "attacks": [
      {
        "name": {
          "ja": "腐食性酸"
        },
        "cost": [
          "grass",
          "grass",
          "normal"
        ],
        "damage": "40",
        "text": {
          "ja": "コインをひっくり返します。頭の場合、防御するポケモンが燃やされます。"
        }
      }
    ],
    "retreat_cost": 2
  },
  {
    "id": "asia-e3-011",
    "set_id": "asia-e3",
    "number": "011",
    "category": "pokemon",
    "name": {
      "ja": "Victreebel"
    },
    "pokemon": [
      "Victreebel"
    ],
    "illustrator": null,
    "rarity": "holo_rare",
    "regulation_mark": null,
    "variants": [
      {
        "id": "holo",
        "images": {
          "ja": ""
        }
      },
      {
        "id": "stamped",
        "images": {
          "ja": ""
        }
      }
    ],
    "hp": 90,
    "types": [
      "grass"
    ],
    "stage": "stage2",
    "attacks": [
      {
        "name": {
          "ja": "腐食性酸"
        },
        "cost": [
          "grass",
          "grass",
          "normal"
        ],
        "damage": "40",
        "text": {
          "ja": "コインをひっくり返します。頭の場合、防御するポケモンが燃やされます。"
        }
      }
    ],
    "retreat_cost": 2
  },
  {
    "id": "asia-e3-012",
    "set_id": "asia-e3",
    "number": "012",
    "category": "pokemon",
    "name": {
      "ja": "exeggcute"
    },
    "pokemon": [
      "exeggcute"
    ],
    "illustrator": null,
    "rarity": "common",
    "regulation_mark": null,
    "variants": [
      {
        "id": "normal",
        "images": {
          "ja": ""
        }
      },
      {
        "id": "stamped",
        "images": {
          "ja": ""
        }
      }
    ],
    "hp": 40,
    "types": [
      "grass"
    ],
    "stage": "basic",
    "attacks": [
      {
        "name": {
          "ja": "成長が急上昇します"
        },
        "cost": [
          "normal"
        ],
        "damage": "",
        "text": {
          "ja": "手からexeggcuteにエネルギーカードを取り付けます。"
        }
      },
      {
        "name": {
          "ja": "スリープパウダー"
        },
        "cost": [
          "grass"
        ],
        "damage": "10",
        "text": {
          "ja": "防御ポケモンは今眠っています。"
        }
      }
    ],
    "retreat_cost": 1
  },
  {
    "id": "asia-e3-013",
    "set_id": "asia-e3",
    "number": "013",
    "category": "pokemon",
    "name": {
      "ja": "exeggutor"
    },
    "pokemon": [
      "exeggutor"
    ],
    "illustrator": null,
    "rarity": "rare",
    "regulation_mark": null,
    "variants": [
      {
        "id": "normal",
        "images": {
          "ja": ""
        }
      },
      {
        "id": "stamped",
        "images": {
          "ja": ""
        }
      }
    ],
    "hp": 80,
    "types": [
      "grass"
    ],
    "stage": "stage1",
    "attacks": [
      {
        "name": {
          "ja": "スーパーエッグスロシオン"
        },
        "cost": [
          "normal"
        ],
        "damage": "",
        "text": {
          "ja": "ポケモンの任意の数に接続されたエネルギーカードを任意の数に捨てます。この方法で破棄されたエネルギーカードの数に等しい数のコインをひっくり返します。この攻撃は、ヘッド数の40回のダメージ倍になります。"
        }
      },
      {
        "name": {
          "ja": "ショットと呼ばれます"
        },
        "cost": [
          "grass"
        ],
        "damage": "",
        "text": {
          "ja": "対戦相手のベンチポケモンを1つ選択します。この攻撃は、exeggutorに取り付けられた草のエネルギーの量を10回ダメージします。 （ベンチポケモンに衰弱や抵抗を適用しないでください。）"
        }
      }
    ],
    "retreat_cost": 1
  },
  {
    "id": "asia-e3-014",
    "set_id": "asia-e3",
    "number": "014",
    "category": "pokemon",
    "name": {
      "ja": "exeggutor"
    },
    "pokemon": [
      "exeggutor"
    ],
    "illustrator": null,
    "rarity": "holo_rare",
    "regulation_mark": null,
    "variants": [
      {
        "id": "holo",
        "images": {
          "ja": ""
        }
      },
      {
        "id": "stamped",
        "images": {
          "ja": ""
        }
      }
    ],
    "hp": 80,
    "types": [
      "grass"
    ],
    "stage": "stage1",
    "attacks": [
      {
        "name": {
          "ja": "スーパーエッグスロシオン"
        },
        "cost": [
          "normal"
        ],
        "damage": "",
        "text": {
          "ja": "ポケモンの任意の数に接続されたエネルギーカードを任意の数に捨てます。この方法で破棄されたエネルギーカードの数に等しい数のコインをひっくり返します。この攻撃は、ヘッド数の40回のダメージ倍になります。"
        }
      },
      {
        "name": {
          "ja": "ショットと呼ばれます"
        },
        "cost": [
          "grass"
        ],
        "damage": "",
        "text": {
          "ja": "対戦相手のベンチポケモンを1つ選択します。この攻撃は、exeggutorに取り付けられた草のエネルギーの量を10回ダメージします。 （ベンチポケモンに衰弱や抵抗を適用しないでください。）"
        }
      }
    ],
    "retreat_cost": 1
  },
  {
    "id": "asia-e3-015",
    "set_id": "asia-e3",
    "number": "015",
    "category": "pokemon",
    "name": {
      "ja": "タンゲラ"
    },
    "pokemon": [
      "タンゲラ"
    ],
    "illustrator": null,
    "rarity": "common",
    "regulation_mark": null,
    "variants": [
      {
        "id": "normal",
        "images": {
          "ja": ""
        }
      },
      {
        "id": "stamped",
        "images": {
          "ja": ""
        }
      }
    ],
    "hp": 60,
    "types": [
      "grass"
    ],
    "stage": "basic",
    "attacks": [
      {
        "name": {
          "ja": "くすぐるブドウ"
        },
        "cost": [
          "normal",
          "normal"
        ],
        "damage": "10",
        "text": {
          "ja": "コインをひっくり返します。頭の場合、防衛ポケモンは相手の次のターン中に攻撃することはできません。"
        }
      },
      {
        "name": {
          "ja": "ダブルキック"
        },
        "cost": [
          "grass",
          "normal",
          "normal"
        ],
        "damage": "",
        "text": {
          "ja": "2つのコインをフリップします。この攻撃は、ヘッド数の30回のダメージ時間を実行します。"
        }
      }
    ],
    "retreat_cost": 2
  },
  {
    "id": "asia-e3-016",
    "set_id": "asia-e3",
    "number": "016",
    "category": "pokemon",
    "name": {
      "ja": "スキスター"
    },
    "pokemon": [
      "スキスター"
    ],
    "illustrator": null,
    "rarity": "common",
    "regulation_mark": null,
    "variants": [
      {
        "id": "normal",
        "images": {
          "ja": ""
        }
      },
      {
        "id": "stamped",
        "images": {
          "ja": ""
        }
      }
    ],
    "hp": 50,
    "types": [
      "grass"
    ],
    "stage": "basic",
    "attacks": [
      {
        "name": {
          "ja": "スラッシュ"
        },
        "cost": [
          "normal"
        ],
        "damage": "10",
        "text": {}
      },
      {
        "name": {
          "ja": "迅速"
        },
        "cost": [
          "grass",
          "normal"
        ],
        "damage": "20",
        "text": {
          "ja": "この攻撃の損傷は、脱力感、抵抗、pok？-Powers、pok？-bodies、または防御ポケモンに対するその他の影響の影響を受けません。"
        }
      }
    ],
    "retreat_cost": 1
  },
  {
    "id": "asia-e3-017",
    "set_id": "asia-e3",
    "number": "017",
    "category": "pokemon",
    "name": {
      "ja": "スキスター"
    },
    "pokemon": [
      "スキスター"
    ],
    "illustrator": null,
    "rarity": "common",
    "regulation_mark": null,
    "variants": [
      {
        "id": "normal",
        "images": {
          "ja": ""
        }
      },
      {
        "id": "stamped",
        "images": {
          "ja": ""
        }
      }
    ],
    "hp": 60,
    "types": [
      "grass"
    ],
    "stage": "basic",
    "attacks": [
      {
        "name": {
          "ja": "クイックターン"
        },
        "cost": [],
        "damage": "",
        "text": {
          "ja": "2つのコインをフリップします。この攻撃は、ヘッド数の10倍のダメージを与えます。"
        }
      },
      {
        "name": {
          "ja": "クロスカット"
        },
        "cost": [
          "normal",
          "normal",
          "normal"
        ],
        "damage": "",
        "text": {
          "ja": "防御ポケモンが進化したポケモンである場合、この攻撃は20ダメージに20回のダメージを与えます。"
        }
      }
    ],
    "retreat_cost": 1
  },
  {
    "id": "asia-e3-018",
    "set_id": "asia-e3",
    "number": "018",
    "category": "pokemon",
    "name": {
      "ja": "ピンシル"
    },
    "pokemon": [
      "ピンシル"
    ],
    "illustrator": null,
    "rarity": "common",
    "regulation_mark": null,
    "variants": [
      {
        "id": "normal",
        "images": {
          "ja": ""
        }
      },
      {
        "id": "stamped",
        "images": {
          "ja": ""
        }
      }
    ],
    "hp": 60,
    "types": [
      "grass"
    ],
    "stage": "basic",
    "attacks": [
      {
        "name": {
          "ja": "ホーングラブ"
        },
        "cost": [
          "normal",
          "normal"
        ],
        "damage": "20",
        "text": {
          "ja": "コインをひっくり返します。頭の場合、防御ポケモンは麻痺しています。尾の場合、この攻撃は何もしません。"
        }
      },
      {
        "name": {
          "ja": "スーパースライス"
        },
        "cost": [
          "grass",
          "grass",
          "normal"
        ],
        "damage": "90",
        "text": {
          "ja": "2つのコインをフリップします。どちらかが尾の場合、この攻撃は何もしません。"
        }
      }
    ],
    "retreat_cost": 1
  },
  {
    "id": "asia-e3-019",
    "set_id": "asia-e3",
    "number": "019",
    "category": "pokemon",
    "name": {
      "ja": "Bellossom"
    },
    "pokemon": [
      "Bellossom"
    ],
    "illustrator": null,
    "rarity": "rare",
    "regulation_mark": null,
    "variants": [
      {
        "id": "normal",
        "images": {
          "ja": ""
        }
      },
      {
        "id": "stamped",
        "images": {
          "ja": ""
        }
      }
    ],
    "hp": 90,
    "types": [
      "grass"
    ],
    "stage": "stage2",
    "attacks": [
      {
        "name": {
          "ja": "ナイフの葉"
        },
        "cost": [
          "grass",
          "grass",
          "normal"
        ],
        "damage": "",
        "text": {
          "ja": "3コインをフリップします。この攻撃は、ヘッド数の30回のダメージ時間を実行します。"
        }
      }
    ],
    "retreat_cost": 2
  },
  {
    "id": "asia-e3-020",
    "set_id": "asia-e3",
    "number": "020",
    "category": "pokemon",
    "name": {
      "ja": "Bellossom"
    },
    "pokemon": [
      "Bellossom"
    ],
    "illustrator": null,
    "rarity": "holo_rare",
    "regulation_mark": null,
    "variants": [
      {
        "id": "normal",
        "images": {
          "ja": ""
        }
      }
    ],
    "hp": 90,
    "types": [
      "grass"
    ],
    "stage": "stage2",
    "attacks": [
      {
        "name": {
          "ja": "ナイフの葉"
        },
        "cost": [
          "grass",
          "grass",
          "normal"
        ],
        "damage": "",
        "text": {
          "ja": "3コインをフリップします。この攻撃は、ヘッド数の30回のダメージ時間を実行します。"
        }
      }
    ],
    "retreat_cost": 2
  },
  {
    "id": "asia-e3-021",
    "set_id": "asia-e3",
    "number": "021",
    "category": "pokemon",
    "name": {
      "ja": "Vulpix"
    },
    "pokemon": [
      "Vulpix"
    ],
    "illustrator": null,
    "rarity": "common",
    "regulation_mark": null,
    "variants": [
      {
        "id": "normal",
        "images": {
          "ja": ""
        }
      },
      {
        "id": "stamped",
        "images": {
          "ja": ""
        }
      }
    ],
    "hp": 50,
    "types": [
      "fire"
    ],
    "stage": "basic",
    "attacks": [
      {
        "name": {
          "ja": "火を集めます"
        },
        "cost": [
          "fire"
        ],
        "damage": "10",
        "text": {
          "ja": "廃棄パイルに火災エネルギーカードがある場合は、コインをひっくり返します。頭の場合は、それらの1つをVulpixに取り付けます。"
        }
      }
    ],
    "retreat_cost": 1
  },
  {
    "id": "asia-e3-022",
    "set_id": "asia-e3",
    "number": "022",
    "category": "pokemon",
    "name": {
      "ja": "ニネタール"
    },
    "pokemon": [
      "ニネタール"
    ],
    "illustrator": null,
    "rarity": "rare",
    "regulation_mark": null,
    "variants": [
      {
        "id": "normal",
        "images": {
          "ja": ""
        }
      },
      {
        "id": "stamped",
        "images": {
          "ja": ""
        }
      }
    ],
    "hp": 80,
    "types": [
      "fire"
    ],
    "stage": "stage1",
    "attacks": [
      {
        "name": {
          "ja": "奇跡の尾"
        },
        "cost": [
          "fire"
        ],
        "damage": "10",
        "text": {
          "ja": "コインをひっくり返します。頭の場合は、特別な状態を選択します（眠り、燃やし、混乱し、麻痺し、毒されます）。防御ポケモンは現在、その特別な状態の影響を受けています。"
        }
      },
      {
        "name": {
          "ja": "焙煎熱"
        },
        "cost": [
          "fire",
          "normal",
          "normal"
        ],
        "damage": "",
        "text": {
          "ja": "防御ポケモンが燃やされた場合、この攻撃は40ダメージに加えて20ダメージを与えます。"
        }
      }
    ],
    "retreat_cost": 1
  },
  {
    "id": "asia-e3-023",
    "set_id": "asia-e3",
    "number": "023",
    "category": "pokemon",
    "name": {
      "ja": "ニネタール"
    },
    "pokemon": [
      "ニネタール"
    ],
    "illustrator": null,
    "rarity": "holo_rare",
    "regulation_mark": null,
    "variants": [
      {
        "id": "normal",
        "images": {
          "ja": ""
        }
      }
    ],
    "hp": 80,
    "types": [
      "fire"
    ],
    "stage": "stage1",
    "attacks": [
      {
        "name": {
          "ja": "奇跡の尾"
        },
        "cost": [
          "fire"
        ],
        "damage": "10",
        "text": {
          "ja": "コインをひっくり返します。頭の場合は、特別な状態を選択します（眠り、燃やし、混乱し、麻痺し、毒されます）。防御ポケモンは現在、その特別な状態の影響を受けています。"
        }
      },
      {
        "name": {
          "ja": "焙煎熱"
        },
        "cost": [
          "fire",
          "normal",
          "normal"
        ],
        "damage": "",
        "text": {
          "ja": "防御ポケモンが燃やされた場合、この攻撃は40ダメージに加えて20ダメージを与えます。"
        }
      }
    ],
    "retreat_cost": 1
  },
  {
    "id": "asia-e3-024",
    "set_id": "asia-e3",
    "number": "024",
    "category": "pokemon",
    "name": {
      "ja": "ポニータ"
    },
    "pokemon": [
      "ポニータ"
    ],
    "illustrator": null,
    "rarity": "common",
    "regulation_mark": null,
    "variants": [
      {
        "id": "normal",
        "images": {
          "ja": ""
        }
      },
      {
        "id": "stamped",
        "images": {
          "ja": ""
        }
      }
    ],
    "hp": 40,
    "types": [
      "fire"
    ],
    "stage": "basic",
    "attacks": [
      {
        "name": {
          "ja": "取り組む"
        },
        "cost": [
          "normal"
        ],
        "damage": "10",
        "text": {}
      },
      {
        "name": {
          "ja": "ember"
        },
        "cost": [
          "fire",
          "normal"
        ],
        "damage": "30",
        "text": {
          "ja": "Ponytaに取り付けられた消防エネルギーカードを捨てます。"
        }
      }
    ],
    "retreat_cost": 1
  },
  {
    "id": "asia-e3-025",
    "set_id": "asia-e3",
    "number": "025",
    "category": "pokemon",
    "name": {
      "ja": "Rapidash"
    },
    "pokemon": [
      "Rapidash"
    ],
    "illustrator": null,
    "rarity": "uncommon",
    "regulation_mark": null,
    "variants": [
      {
        "id": "normal",
        "images": {
          "ja": ""
        }
      },
      {
        "id": "stamped",
        "images": {
          "ja": ""
        }
      }
    ],
    "hp": 70,
    "types": [
      "fire"
    ],
    "stage": "stage1",
    "attacks": [
      {
        "name": {
          "ja": "敏ility性"
        },
        "cost": [
          "normal",
          "normal"
        ],
        "damage": "10",
        "text": {
          "ja": "コインをひっくり返します。ヘッドが、相手の次のターン中に、RapidAshに行われた損害を含む攻撃のすべての影響を防ぎます。"
        }
      },
      {
        "name": {
          "ja": "ギャロップ"
        },
        "cost": [
          "fire",
          "normal",
          "normal"
        ],
        "damage": "",
        "text": {
          "ja": "コインをひっくり返します。頭の場合は、Rapidashに取り付けられた消防エネルギーカードを捨ててください。この攻撃は30ダメージに加えて20ダメージを与えます。"
        }
      }
    ]
  },
  {
    "id": "asia-e3-026",
    "set_id": "asia-e3",
    "number": "026",
    "category": "pokemon",
    "name": {
      "ja": "entei"
    },
    "pokemon": [
      "entei"
    ],
    "illustrator": null,
    "rarity": "rare",
    "regulation_mark": null,
    "variants": [
      {
        "id": "normal",
        "images": {
          "ja": ""
        }
      }
    ],
    "hp": 70,
    "types": [
      "fire"
    ],
    "stage": "basic",
    "attacks": [
      {
        "name": {
          "ja": "牙を燃やします"
        },
        "cost": [
          "fire",
          "normal",
          "normal"
        ],
        "damage": "40",
        "text": {
          "ja": "コインをひっくり返すことができます。頭の場合は、Enteiに取り付けられた消防エネルギーカードを捨て、防御ポケモンが燃やされます。"
        }
      }
    ],
    "retreat_cost": 1
  },
  {
    "id": "asia-e3-027",
    "set_id": "asia-e3",
    "number": "027",
    "category": "pokemon",
    "name": {
      "ja": "entei"
    },
    "pokemon": [
      "entei"
    ],
    "illustrator": null,
    "rarity": "holo_rare",
    "regulation_mark": null,
    "variants": [
      {
        "id": "normal",
        "images": {
          "ja": ""
        }
      }
    ],
    "hp": 70,
    "types": [
      "fire"
    ],
    "stage": "basic",
    "attacks": [
      {
        "name": {
          "ja": "牙を燃やします"
        },
        "cost": [
          "fire",
          "normal",
          "normal"
        ],
        "damage": "40",
        "text": {
          "ja": "コインをひっくり返すことができます。頭の場合は、Enteiに取り付けられた消防エネルギーカードを捨て、防御ポケモンが燃やされます。"
        }
      }
    ],
    "retreat_cost": 1
  },
  {
    "id": "asia-e3-028",
    "set_id": "asia-e3",
    "number": "028",
    "category": "pokemon",
    "name": {
      "ja": "Tentacool"
    },
    "pokemon": [
      "Tentacool"
    ],
    "illustrator": null,
    "rarity": "common",
    "regulation_mark": null,
    "variants": [
      {
        "id": "normal",
        "images": {
          "ja": ""
        }
      },
      {
        "id": "stamped",
        "images": {
          "ja": ""
        }
      }
    ],
    "hp": 50,
    "types": [
      "water"
    ],
    "stage": "basic",
    "attacks": [
      {
        "name": {
          "ja": "毒物"
        },
        "cost": [
          "normal"
        ],
        "damage": "",
        "text": {
          "ja": "コインをひっくり返します。頭の場合、防御ポケモンは現在毒されています。"
        }
      },
      {
        "name": {
          "ja": "回復する"
        },
        "cost": [
          "water"
        ],
        "damage": "",
        "text": {
          "ja": "この攻撃を使用するために、Tentacoolに取り付けられた1つの水エネルギーカードを廃棄します。 Tentacoolからすべてのダメージカウンターを削除します。"
        }
      }
    ],
    "retreat_cost": 1
  },
  {
    "id": "asia-e3-029",
    "set_id": "asia-e3",
    "number": "029",
    "category": "pokemon",
    "name": {
      "ja": "テンタクルエル"
    },
    "pokemon": [
      "テンタクルエル"
    ],
    "illustrator": null,
    "rarity": "rare",
    "regulation_mark": null,
    "variants": [
      {
        "id": "normal",
        "images": {
          "ja": ""
        }
      },
      {
        "id": "stamped",
        "images": {
          "ja": ""
        }
      }
    ],
    "hp": 70,
    "types": [
      "water"
    ],
    "stage": "stage1",
    "attacks": [
      {
        "name": {
          "ja": "毒物"
        },
        "cost": [
          "water",
          "normal"
        ],
        "damage": "20",
        "text": {
          "ja": "コインをひっくり返します。頭の場合、防御ポケモンは現在毒されています。"
        }
      }
    ]
  },
  {
    "id": "asia-e3-030",
    "set_id": "asia-e3",
    "number": "030",
    "category": "pokemon",
    "name": {
      "ja": "テンタクルエル"
    },
    "pokemon": [
      "テンタクルエル"
    ],
    "illustrator": null,
    "rarity": "holo_rare",
    "regulation_mark": null,
    "variants": [
      {
        "id": "holo",
        "images": {
          "ja": ""
        }
      },
      {
        "id": "stamped",
        "images": {
          "ja": ""
        }
      }
    ],
    "hp": 70,
    "types": [
      "water"
    ],
    "stage": "stage1",
    "attacks": [
      {
        "name": {
          "ja": "毒物"
        },
        "cost": [
          "water",
          "normal"
        ],
        "damage": "20",
        "text": {
          "ja": "コインをひっくり返します。頭の場合、防御ポケモンは現在毒されています。"
        }
      }
    ]
  },
  {
    "id": "asia-e3-031",
    "set_id": "asia-e3",
    "number": "031",
    "category": "pokemon",
    "name": {
      "ja": "slowpoke"
    },
    "pokemon": [
      "slowpoke"
    ],
    "illustrator": null,
    "rarity": "common",
    "regulation_mark": null,
    "variants": [
      {
        "id": "normal",
        "images": {
          "ja": ""
        }
      },
      {
        "id": "stamped",
        "images": {
          "ja": ""
        }
      }
    ],
    "hp": 50,
    "types": [
      "water"
    ],
    "stage": "basic",
    "attacks": [
      {
        "name": {
          "ja": "釣りの尾"
        },
        "cost": [
          "normal"
        ],
        "damage": "",
        "text": {
          "ja": "廃棄の山、ベビーポケモン、基本的なポケモン、エボリューションカード、​​または基本エネルギーカードを検索し、対戦相手に見せてから手に入れます。"
        }
      },
      {
        "name": {
          "ja": "噛む"
        },
        "cost": [
          "normal",
          "normal"
        ],
        "damage": "20",
        "text": {}
      }
    ],
    "retreat_cost": 1
  },
  {
    "id": "asia-e3-032",
    "set_id": "asia-e3",
    "number": "032",
    "category": "pokemon",
    "name": {
      "ja": "スローブロ"
    },
    "pokemon": [
      "スローブロ"
    ],
    "illustrator": null,
    "rarity": "uncommon",
    "regulation_mark": null,
    "variants": [
      {
        "id": "normal",
        "images": {
          "ja": ""
        }
      }
    ],
    "hp": 80,
    "types": [
      "water"
    ],
    "stage": "stage1",
    "attacks": [
      {
        "name": {
          "ja": "エネルギー大砲"
        },
        "cost": [
          "water",
          "normal"
        ],
        "damage": "",
        "text": {
          "ja": "この攻撃は、スローブロに付着した各エネルギーに対して30のダメージと10ダメージを10件以上ダメージしますが、この攻撃のエネルギーコストの支払いには使用されません。この方法で20以上のダメージを追加することはできません。"
        }
      }
    ],
    "retreat_cost": 2
  },
  {
    "id": "asia-e3-033",
    "set_id": "asia-e3",
    "number": "033",
    "category": "pokemon",
    "name": {
      "ja": "馬"
    },
    "pokemon": [
      "馬"
    ],
    "illustrator": null,
    "rarity": "common",
    "regulation_mark": null,
    "variants": [
      {
        "id": "normal",
        "images": {
          "ja": ""
        }
      },
      {
        "id": "stamped",
        "images": {
          "ja": ""
        }
      }
    ],
    "hp": 40,
    "types": [
      "water"
    ],
    "stage": "basic",
    "attacks": [
      {
        "name": {
          "ja": "バブル"
        },
        "cost": [
          "water"
        ],
        "damage": "10",
        "text": {
          "ja": "コインをひっくり返します。頭の場合、防御ポケモンは麻痺しています。"
        }
      }
    ],
    "retreat_cost": 1
  },
  {
    "id": "asia-e3-034",
    "set_id": "asia-e3",
    "number": "034",
    "category": "pokemon",
    "name": {
      "ja": "馬"
    },
    "pokemon": [
      "馬"
    ],
    "illustrator": null,
    "rarity": "common",
    "regulation_mark": null,
    "variants": [
      {
        "id": "normal",
        "images": {
          "ja": ""
        }
      },
      {
        "id": "stamped",
        "images": {
          "ja": ""
        }
      }
    ],
    "hp": 50,
    "types": [
      "water"
    ],
    "stage": "basic",
    "attacks": [
      {
        "name": {
          "ja": "逆スラスト"
        },
        "cost": [
          "normal",
          "normal"
        ],
        "damage": "20",
        "text": {
          "ja": "ベンチ付きポケモンを1枚馬に切り替えます。"
        }
      }
    ],
    "retreat_cost": 1
  },
  {
    "id": "asia-e3-035",
    "set_id": "asia-e3",
    "number": "035",
    "category": "pokemon",
    "name": {
      "ja": "シードラ"
    },
    "pokemon": [
      "シードラ"
    ],
    "illustrator": null,
    "rarity": "common",
    "regulation_mark": null,
    "variants": [
      {
        "id": "normal",
        "images": {
          "ja": ""
        }
      },
      {
        "id": "stamped",
        "images": {
          "ja": ""
        }
      }
    ],
    "hp": 70,
    "types": [
      "water"
    ],
    "stage": "stage1",
    "attacks": [
      {
        "name": {
          "ja": "波のスプラッシュ"
        },
        "cost": [
          "water"
        ],
        "damage": "20",
        "text": {}
      },
      {
        "name": {
          "ja": "水の弾丸"
        },
        "cost": [
          "normal",
          "normal",
          "normal"
        ],
        "damage": "",
        "text": {
          "ja": "Seadraに取り付けられた水エネルギーの数に等しい多数のコインをひっくり返します。この攻撃は、30のダメージに加えて、各ヘッドに対してさらに10ダメージを与えます。"
        }
      }
    ],
    "retreat_cost": 1
  },
  {
    "id": "asia-e3-036",
    "set_id": "asia-e3",
    "number": "036",
    "category": "pokemon",
    "name": {
      "ja": "チンチョウ"
    },
    "pokemon": [
      "チンチョウ"
    ],
    "illustrator": null,
    "rarity": "common",
    "regulation_mark": null,
    "variants": [
      {
        "id": "normal",
        "images": {
          "ja": ""
        }
      },
      {
        "id": "stamped",
        "images": {
          "ja": ""
        }
      }
    ],
    "hp": 50,
    "types": [
      "water"
    ],
    "stage": "basic",
    "attacks": [
      {
        "name": {
          "ja": "フロート"
        },
        "cost": [
          "normal"
        ],
        "damage": "",
        "text": {
          "ja": "コインをひっくり返します。ヘッドの場合、対戦相手の次のターン中に、チンチョウに行われた損害を含む攻撃のすべての影響を防ぎます。"
        }
      },
      {
        "name": {
          "ja": "ヘッドバット"
        },
        "cost": [
          "normal",
          "normal"
        ],
        "damage": "20",
        "text": {}
      }
    ],
    "retreat_cost": 1
  },
  {
    "id": "asia-e3-037",
    "set_id": "asia-e3",
    "number": "037",
    "category": "pokemon",
    "name": {
      "ja": "ラントン"
    },
    "pokemon": [
      "ラントン"
    ],
    "illustrator": null,
    "rarity": "uncommon",
    "regulation_mark": null,
    "variants": [
      {
        "id": "normal",
        "images": {
          "ja": ""
        }
      },
      {
        "id": "stamped",
        "images": {
          "ja": ""
        }
      }
    ],
    "hp": 80,
    "types": [
      "water"
    ],
    "stage": "stage1",
    "attacks": [
      {
        "name": {
          "ja": "稲妻"
        },
        "cost": [
          "lightning"
        ],
        "damage": "20",
        "text": {}
      },
      {
        "name": {
          "ja": "伝導"
        },
        "cost": [
          "normal",
          "normal",
          "normal"
        ],
        "damage": "",
        "text": {
          "ja": "Lanturnに取り付けられたすべての稲妻エネルギーカードを捨てます。廃棄した稲妻エネルギーカードの数に等しい多数のコインをひっくり返します。この攻撃は、30のダメージに加えて、各ヘッドに対してさらに40のダメージを与えます。"
        }
      }
    ],
    "retreat_cost": 1
  },
  {
    "id": "asia-e3-038",
    "set_id": "asia-e3",
    "number": "038",
    "category": "pokemon",
    "name": {
      "ja": "REMORAID"
    },
    "pokemon": [
      "REMORAID"
    ],
    "illustrator": null,
    "rarity": "common",
    "regulation_mark": null,
    "variants": [
      {
        "id": "normal",
        "images": {
          "ja": ""
        }
      },
      {
        "id": "stamped",
        "images": {
          "ja": ""
        }
      }
    ],
    "hp": 50,
    "types": [
      "water"
    ],
    "stage": "basic",
    "attacks": [
      {
        "name": {
          "ja": "スプラッタ"
        },
        "cost": [
          "water"
        ],
        "damage": "",
        "text": {
          "ja": "プレイ中の対戦相手のポケモンを1つ選択します。この攻撃は、そのポケモンに10ダメージを与えます。この攻撃に弱さや抵抗を適用しないでください。"
        }
      }
    ],
    "retreat_cost": 1
  },
  {
    "id": "asia-e3-039",
    "set_id": "asia-e3",
    "number": "039",
    "category": "pokemon",
    "name": {
      "ja": "オクリリー"
    },
    "pokemon": [
      "オクリリー"
    ],
    "illustrator": null,
    "rarity": "rare",
    "regulation_mark": null,
    "variants": [
      {
        "id": "normal",
        "images": {
          "ja": ""
        }
      },
      {
        "id": "stamped",
        "images": {
          "ja": ""
        }
      }
    ],
    "hp": 80,
    "types": [
      "water"
    ],
    "stage": "stage1",
    "attacks": [
      {
        "name": {
          "ja": "煙幕"
        },
        "cost": [
          "water",
          "normal",
          "normal"
        ],
        "damage": "40",
        "text": {
          "ja": "防衛ポケモンが相手の次のターン中に攻撃を試みた場合、対戦相手はコインをひっくり返します。尾の場合、その攻撃は何もしません。"
        }
      }
    ],
    "retreat_cost": 2
  },
  {
    "id": "asia-e3-040",
    "set_id": "asia-e3",
    "number": "040",
    "category": "pokemon",
    "name": {
      "ja": "オクリリー"
    },
    "pokemon": [
      "オクリリー"
    ],
    "illustrator": null,
    "rarity": "holo_rare",
    "regulation_mark": null,
    "variants": [
      {
        "id": "holo",
        "images": {
          "ja": ""
        }
      },
      {
        "id": "stamped",
        "images": {
          "ja": ""
        }
      }
    ],
    "hp": 80,
    "types": [
      "water"
    ],
    "stage": "stage1",
    "attacks": [
      {
        "name": {
          "ja": "煙幕"
        },
        "cost": [
          "water",
          "normal",
          "normal"
        ],
        "damage": "40",
        "text": {
          "ja": "防衛ポケモンが相手の次のターン中に攻撃を試みた場合、対戦相手はコインをひっくり返します。尾の場合、その攻撃は何もしません。"
        }
      }
    ],
    "retreat_cost": 2
  },
  {
    "id": "asia-e3-041",
    "set_id": "asia-e3",
    "number": "041",
    "category": "pokemon",
    "name": {
      "ja": "キングドラ"
    },
    "pokemon": [
      "キングドラ"
    ],
    "illustrator": null,
    "rarity": "rare",
    "regulation_mark": null,
    "variants": [
      {
        "id": "normal",
        "images": {
          "ja": ""
        }
      },
      {
        "id": "stamped",
        "images": {
          "ja": ""
        }
      }
    ],
    "hp": 120,
    "types": [
      "water"
    ],
    "stage": "stage2",
    "attacks": [
      {
        "name": {
          "ja": "急流"
        },
        "cost": [
          "water",
          "water",
          "normal",
          "normal"
        ],
        "damage": "50",
        "text": {
          "ja": "コインをひっくり返します。頭の場合は、ディフェンディングポケモンに取り付けられた1つのエネルギーカードを捨ててください。"
        }
      }
    ],
    "retreat_cost": 3
  },
  {
    "id": "asia-e3-042",
    "set_id": "asia-e3",
    "number": "042",
    "category": "pokemon",
    "name": {
      "ja": "キングドラ"
    },
    "pokemon": [
      "キングドラ"
    ],
    "illustrator": null,
    "rarity": "holo_rare",
    "regulation_mark": null,
    "variants": [
      {
        "id": "holo",
        "images": {
          "ja": ""
        }
      }
    ],
    "hp": 120,
    "types": [
      "water"
    ],
    "stage": "stage2",
    "attacks": [
      {
        "name": {
          "ja": "急流"
        },
        "cost": [
          "water",
          "water",
          "normal",
          "normal"
        ],
        "damage": "50",
        "text": {
          "ja": "コインをひっくり返します。頭の場合は、ディフェンディングポケモンに取り付けられた1つのエネルギーカードを捨ててください。"
        }
      }
    ],
    "retreat_cost": 3
  },
  {
    "id": "asia-e3-043",
    "set_id": "asia-e3",
    "number": "043",
    "category": "pokemon",
    "name": {
      "ja": "チンチョウ"
    },
    "pokemon": [
      "チンチョウ"
    ],
    "illustrator": null,
    "rarity": "common",
    "regulation_mark": null,
    "variants": [
      {
        "id": "normal",
        "images": {
          "ja": ""
        }
      },
      {
        "id": "stamped",
        "images": {
          "ja": ""
        }
      }
    ],
    "hp": 50,
    "types": [
      "lightning"
    ],
    "stage": "basic",
    "attacks": [
      {
        "name": {
          "ja": "衝撃"
        },
        "cost": [
          "normal"
        ],
        "damage": "",
        "text": {
          "ja": "コインをひっくり返します。頭の場合、防御ポケモンは麻痺しています。"
        }
      },
      {
        "name": {
          "ja": "レイを混乱させます"
        },
        "cost": [
          "lightning",
          "normal"
        ],
        "damage": "10",
        "text": {
          "ja": "コインをひっくり返します。頭の場合、防御ポケモンは混乱しています。"
        }
      }
    ],
    "retreat_cost": 1
  },
  {
    "id": "asia-e3-044",
    "set_id": "asia-e3",
    "number": "044",
    "category": "pokemon",
    "name": {
      "ja": "ラントン"
    },
    "pokemon": [
      "ラントン"
    ],
    "illustrator": null,
    "rarity": "rare",
    "regulation_mark": null,
    "variants": [
      {
        "id": "normal",
        "images": {
          "ja": ""
        }
      },
      {
        "id": "stamped",
        "images": {
          "ja": ""
        }
      }
    ],
    "hp": 80,
    "types": [
      "lightning"
    ],
    "stage": "stage1",
    "attacks": [
      {
        "name": {
          "ja": "電気タックル"
        },
        "cost": [
          "normal",
          "normal"
        ],
        "damage": "",
        "text": {
          "ja": "この攻撃は、ラントゥルンに取り付けられた各稲妻エネルギーに対して20のダメージに加えて10ダメージを与えます。コインをひっくり返します。尾の場合、ラントゥルンは、それに取り付けられた各稲妻エネルギーに対してそれ自体に10ダメージを与えます。"
        }
      }
    ],
    "retreat_cost": 1
  },
  {
    "id": "asia-e3-045",
    "set_id": "asia-e3",
    "number": "045",
    "category": "pokemon",
    "name": {
      "ja": "ラントン"
    },
    "pokemon": [
      "ラントン"
    ],
    "illustrator": null,
    "rarity": "holo_rare",
    "regulation_mark": null,
    "variants": [
      {
        "id": "normal",
        "images": {
          "ja": ""
        }
      }
    ],
    "hp": 80,
    "types": [
      "lightning"
    ],
    "stage": "stage1",
    "attacks": [
      {
        "name": {
          "ja": "電気タックル"
        },
        "cost": [
          "normal",
          "normal"
        ],
        "damage": "",
        "text": {
          "ja": "この攻撃は、ラントゥルンに取り付けられた各稲妻エネルギーに対して20のダメージに加えて10ダメージを与えます。コインをひっくり返します。尾の場合、ラントゥルンは、それに取り付けられた各稲妻エネルギーに対してそれ自体に10ダメージを与えます。"
        }
      }
    ],
    "retreat_cost": 1
  },
  {
    "id": "asia-e3-046",
    "set_id": "asia-e3",
    "number": "046",
    "category": "pokemon",
    "name": {
      "ja": "Mareep"
    },
    "pokemon": [
      "Mareep"
    ],
    "illustrator": null,
    "rarity": "common",
    "regulation_mark": null,
    "variants": [
      {
        "id": "normal",
        "images": {
          "ja": ""
        }
      }
    ],
    "hp": 40,
    "types": [
      "lightning"
    ],
    "stage": "basic",
    "attacks": [
      {
        "name": {
          "ja": "充電"
        },
        "cost": [
          "normal"
        ],
        "damage": "",
        "text": {
          "ja": "廃棄パイルからMareepに1つの稲妻エネルギーカードを取り付けます。"
        }
      },
      {
        "name": {
          "ja": "テールスラップ"
        },
        "cost": [
          "lightning",
          "normal"
        ],
        "damage": "20",
        "text": {}
      }
    ],
    "retreat_cost": 1
  },
  {
    "id": "asia-e3-047",
    "set_id": "asia-e3",
    "number": "047",
    "category": "pokemon",
    "name": {
      "ja": "フラフィー"
    },
    "pokemon": [
      "フラフィー"
    ],
    "illustrator": null,
    "rarity": "common",
    "regulation_mark": null,
    "variants": [
      {
        "id": "normal",
        "images": {
          "ja": ""
        }
      },
      {
        "id": "stamped",
        "images": {
          "ja": ""
        }
      }
    ],
    "hp": 80,
    "types": [
      "lightning"
    ],
    "stage": "stage1",
    "attacks": [
      {
        "name": {
          "ja": "サンダーショック"
        },
        "cost": [
          "normal"
        ],
        "damage": "10",
        "text": {
          "ja": "コインをひっくり返します。頭の場合、防御ポケモンは麻痺しています。"
        }
      },
      {
        "name": {
          "ja": "スパーク"
        },
        "cost": [
          "lightning",
          "lightning",
          "normal"
        ],
        "damage": "30",
        "text": {
          "ja": "対戦相手がベンチでポケモンを持っている場合は、1つを選択すると、この攻撃は10ダメージを与えます。 （ベンチポケモンに衰弱と抵抗を適用しないでください。）"
        }
      }
    ],
    "retreat_cost": 1
  },
  {
    "id": "asia-e3-048",
    "set_id": "asia-e3",
    "number": "048",
    "category": "pokemon",
    "name": {
      "ja": "アンファロス"
    },
    "pokemon": [
      "アンファロス"
    ],
    "illustrator": null,
    "rarity": "rare",
    "regulation_mark": null,
    "variants": [
      {
        "id": "normal",
        "images": {
          "ja": ""
        }
      },
      {
        "id": "stamped",
        "images": {
          "ja": ""
        }
      }
    ],
    "hp": 100,
    "types": [
      "lightning"
    ],
    "stage": "stage2",
    "attacks": [
      {
        "name": {
          "ja": "サンダーショック"
        },
        "cost": [
          "lightning"
        ],
        "damage": "20",
        "text": {
          "ja": "コインをひっくり返します。頭の場合、防御ポケモンは麻痺しています。"
        }
      },
      {
        "name": {
          "ja": "エネルギーを反映します"
        },
        "cost": [
          "lightning",
          "lightning",
          "normal"
        ],
        "damage": "50",
        "text": {
          "ja": "ベンチ付きポケモンがあり、Ampharosに基本的なエネルギーカードが付いている場合は、それらのエネルギーカードの1つを取り、ポケモンの1つに取り付けます。"
        }
      }
    ],
    "retreat_cost": 2
  },
  {
    "id": "asia-e3-049",
    "set_id": "asia-e3",
    "number": "049",
    "category": "pokemon",
    "name": {
      "ja": "アンファロス"
    },
    "pokemon": [
      "アンファロス"
    ],
    "illustrator": null,
    "rarity": "holo_rare",
    "regulation_mark": null,
    "variants": [
      {
        "id": "holo",
        "images": {
          "ja": ""
        }
      },
      {
        "id": "stamped",
        "images": {
          "ja": ""
        }
      }
    ],
    "hp": 100,
    "types": [
      "lightning"
    ],
    "stage": "stage2",
    "attacks": [
      {
        "name": {
          "ja": "サンダーショック"
        },
        "cost": [
          "lightning"
        ],
        "damage": "20",
        "text": {
          "ja": "コインをひっくり返します。頭の場合、防御ポケモンは麻痺しています。"
        }
      },
      {
        "name": {
          "ja": "エネルギーを反映します"
        },
        "cost": [
          "lightning",
          "lightning",
          "normal"
        ],
        "damage": "50",
        "text": {
          "ja": "ベンチ付きポケモンがあり、Ampharosに基本的なエネルギーカードが付いている場合は、それらのエネルギーカードの1つを取り、ポケモンの1つに取り付けます。"
        }
      }
    ],
    "retreat_cost": 2
  },
  {
    "id": "asia-e3-050",
    "set_id": "asia-e3",
    "number": "050",
    "category": "pokemon",
    "name": {
      "ja": "exeggcute"
    },
    "pokemon": [
      "exeggcute"
    ],
    "illustrator": null,
    "rarity": "common",
    "regulation_mark": null,
    "variants": [
      {
        "id": "normal",
        "images": {
          "ja": ""
        }
      },
      {
        "id": "stamped",
        "images": {
          "ja": ""
        }
      }
    ],
    "hp": 50,
    "types": [
      "psychic"
    ],
    "stage": "basic",
    "attacks": [
      {
        "name": {
          "ja": "連続した卵の幅"
        },
        "cost": [
          "normal"
        ],
        "damage": "",
        "text": {
          "ja": "尾がなくなるまでコインをひっくり返します。この攻撃は、ヘッド数の10倍のダメージを与えます。"
        }
      },
      {
        "name": {
          "ja": "エネルギーサポート"
        },
        "cost": [
          "psychic"
        ],
        "damage": "",
        "text": {
          "ja": "コインをひっくり返します。頭の場合は、デッキを検索してサイキックエネルギーカードを探して、ベンチ付きポケモン1枚に取り付けます。その後、デッキをシャッフルします。"
        }
      }
    ],
    "retreat_cost": 1
  },
  {
    "id": "asia-e3-051",
    "set_id": "asia-e3",
    "number": "051",
    "category": "pokemon",
    "name": {
      "ja": "exeggutor"
    },
    "pokemon": [
      "exeggutor"
    ],
    "illustrator": null,
    "rarity": "uncommon",
    "regulation_mark": null,
    "variants": [
      {
        "id": "normal",
        "images": {
          "ja": ""
        }
      },
      {
        "id": "stamped",
        "images": {
          "ja": ""
        }
      }
    ],
    "hp": 80,
    "types": [
      "psychic"
    ],
    "stage": "stage1",
    "attacks": [
      {
        "name": {
          "ja": "大きな卵の幅"
        },
        "cost": [
          "normal"
        ],
        "damage": "",
        "text": {
          "ja": "exeggutorに取り付けられたエネルギーの量に等しい多数のコインをひっくり返します。この攻撃は、ヘッド数の20倍のダメージを与えます。"
        }
      },
      {
        "name": {
          "ja": "横卵の幅"
        },
        "cost": [
          "psychic",
          "normal",
          "normal"
        ],
        "damage": "",
        "text": {
          "ja": "すべてのベンチポケモンに取り付けられたエネルギーの量に等しい多数のコインをひっくり返します。この攻撃は、30のダメージに加えて、各ヘッドに対してさらに10ダメージを与えます。"
        }
      }
    ],
    "retreat_cost": 1
  },
  {
    "id": "asia-e3-052",
    "set_id": "asia-e3",
    "number": "052",
    "category": "pokemon",
    "name": {
      "ja": "スローキング"
    },
    "pokemon": [
      "スローキング"
    ],
    "illustrator": null,
    "rarity": "rare",
    "regulation_mark": null,
    "variants": [
      {
        "id": "normal",
        "images": {
          "ja": ""
        }
      }
    ],
    "hp": 80,
    "types": [
      "psychic"
    ],
    "stage": "stage1",
    "attacks": [
      {
        "name": {
          "ja": "バーストハンド"
        },
        "cost": [
          "normal"
        ],
        "damage": "",
        "text": {
          "ja": "相手の手を見てください。この攻撃は、エネルギーカードの数の10倍のダメージを与えます。"
        }
      },
      {
        "name": {
          "ja": "シャッフル攻撃"
        },
        "cost": [
          "psychic",
          "normal",
          "normal"
        ],
        "damage": "40",
        "text": {
          "ja": "防御ポケモンに接続されたエネルギーカードの数に等しい相手のデッキの上にある多くのカードを見てください。それらのカードを任意の順序に置き、対戦相手のデッキの上に戻します。"
        }
      }
    ],
    "retreat_cost": 1
  },
  {
    "id": "asia-e3-053",
    "set_id": "asia-e3",
    "number": "053",
    "category": "pokemon",
    "name": {
      "ja": "スローキング"
    },
    "pokemon": [
      "スローキング"
    ],
    "illustrator": null,
    "rarity": "holo_rare",
    "regulation_mark": null,
    "variants": [
      {
        "id": "normal",
        "images": {
          "ja": ""
        }
      }
    ],
    "hp": 80,
    "types": [
      "psychic"
    ],
    "stage": "stage1",
    "attacks": [
      {
        "name": {
          "ja": "バーストハンド"
        },
        "cost": [
          "normal"
        ],
        "damage": "",
        "text": {
          "ja": "相手の手を見てください。この攻撃は、エネルギーカードの数の10倍のダメージを与えます。"
        }
      },
      {
        "name": {
          "ja": "シャッフル攻撃"
        },
        "cost": [
          "psychic",
          "normal",
          "normal"
        ],
        "damage": "40",
        "text": {
          "ja": "防御ポケモンに接続されたエネルギーカードの数に等しい相手のデッキの上にある多くのカードを見てください。それらのカードを任意の順序に置き、対戦相手のデッキの上に戻します。"
        }
      }
    ],
    "retreat_cost": 1
  },
  {
    "id": "asia-e3-054",
    "set_id": "asia-e3",
    "number": "054",
    "category": "pokemon",
    "name": {
      "ja": "マンキー"
    },
    "pokemon": [
      "マンキー"
    ],
    "illustrator": null,
    "rarity": "common",
    "regulation_mark": null,
    "variants": [
      {
        "id": "normal",
        "images": {
          "ja": ""
        }
      },
      {
        "id": "stamped",
        "images": {
          "ja": ""
        }
      }
    ],
    "hp": 40,
    "types": [
      "fighting"
    ],
    "stage": "basic",
    "attacks": [
      {
        "name": {
          "ja": "マグ"
        },
        "cost": [
          "fighting"
        ],
        "damage": "10",
        "text": {
          "ja": "ダメージを与える前に、防御ポケモンに取り付けられたすべてのトレーナーカードを捨ててください。"
        }
      },
      {
        "name": {
          "ja": "怒り"
        },
        "cost": [
          "normal",
          "normal"
        ],
        "damage": "",
        "text": {
          "ja": "この攻撃は、マンキーのダメージカウンターごとに10ダメージに加えて10ダメージを与えます。"
        }
      }
    ],
    "retreat_cost": 1
  },
  {
    "id": "asia-e3-055",
    "set_id": "asia-e3",
    "number": "055",
    "category": "pokemon",
    "name": {
      "ja": "プライム"
    },
    "pokemon": [
      "プライム"
    ],
    "illustrator": null,
    "rarity": "uncommon",
    "regulation_mark": null,
    "variants": [
      {
        "id": "normal",
        "images": {
          "ja": ""
        }
      },
      {
        "id": "stamped",
        "images": {
          "ja": ""
        }
      }
    ],
    "hp": 80,
    "types": [
      "fighting"
    ],
    "stage": "stage1",
    "attacks": [
      {
        "name": {
          "ja": "空手チョップ"
        },
        "cost": [
          "fighting",
          "normal"
        ],
        "damage": "",
        "text": {
          "ja": "この攻撃による損傷は、Primeapeの各ダメージカウンターで10倍に減少します。"
        }
      },
      {
        "name": {
          "ja": "突然の充電"
        },
        "cost": [
          "fighting",
          "normal",
          "normal"
        ],
        "damage": "40",
        "text": {
          "ja": "Primeapeはそれ自体に10ダメージを与えます。次に、対戦相手は、ベンチ付きポケモンの1つで防御ポケモンを切り替えます。"
        }
      }
    ],
    "retreat_cost": 1
  },
  {
    "id": "asia-e3-056",
    "set_id": "asia-e3",
    "number": "056",
    "category": "pokemon",
    "name": {
      "ja": "onix"
    },
    "pokemon": [
      "onix"
    ],
    "illustrator": null,
    "rarity": "common",
    "regulation_mark": null,
    "variants": [
      {
        "id": "normal",
        "images": {
          "ja": ""
        }
      },
      {
        "id": "stamped",
        "images": {
          "ja": ""
        }
      }
    ],
    "hp": 60,
    "types": [
      "fighting"
    ],
    "stage": "basic",
    "attacks": [
      {
        "name": {
          "ja": "打ち砕く"
        },
        "cost": [
          "fighting",
          "normal"
        ],
        "damage": "",
        "text": {
          "ja": "Onixに取り付けられたエネルギーの量に等しい多数のコインをひっくり返します。この攻撃は、ヘッド数の20倍のダメージを与えます。"
        }
      }
    ],
    "retreat_cost": 2
  },
  {
    "id": "asia-e3-057",
    "set_id": "asia-e3",
    "number": "057",
    "category": "pokemon",
    "name": {
      "ja": "sudowoodo"
    },
    "pokemon": [
      "sudowoodo"
    ],
    "illustrator": null,
    "rarity": "rare",
    "regulation_mark": null,
    "variants": [
      {
        "id": "normal",
        "images": {
          "ja": ""
        }
      }
    ],
    "hp": 60,
    "types": [
      "fighting"
    ],
    "stage": "basic",
    "attacks": [
      {
        "name": {
          "ja": "コピー"
        },
        "cost": [
          "normal"
        ],
        "damage": "",
        "text": {
          "ja": "防御ポケモンの攻撃の1つを選択します。その攻撃をコピーします。 Sudowoodoにその攻撃を使用するのに必要なエネルギーがない場合、この攻撃は何もしません。 （その攻撃を使用するために必要な他のことをまだしなければなりません。）"
        }
      },
      {
        "name": {
          "ja": "エネルギーの引き分け"
        },
        "cost": [
          "fighting"
        ],
        "damage": "",
        "text": {
          "ja": "デッキを検索して、基本的なエネルギーカードを調べ、sudowoodoに添付してください。その後、デッキをシャッフルします。"
        }
      }
    ],
    "retreat_cost": 2
  },
  {
    "id": "asia-e3-058",
    "set_id": "asia-e3",
    "number": "058",
    "category": "pokemon",
    "name": {
      "ja": "sudowoodo"
    },
    "pokemon": [
      "sudowoodo"
    ],
    "illustrator": null,
    "rarity": "holo_rare",
    "regulation_mark": null,
    "variants": [
      {
        "id": "holo",
        "images": {
          "ja": ""
        }
      },
      {
        "id": "stamped",
        "images": {
          "ja": ""
        }
      }
    ],
    "hp": 60,
    "types": [
      "fighting"
    ],
    "stage": "basic",
    "attacks": [
      {
        "name": {
          "ja": "コピー"
        },
        "cost": [
          "normal"
        ],
        "damage": "",
        "text": {
          "ja": "防御ポケモンの攻撃の1つを選択します。その攻撃をコピーします。 Sudowoodoにその攻撃を使用するのに必要なエネルギーがない場合、この攻撃は何もしません。 （その攻撃を使用するために必要な他のことをまだしなければなりません。）"
        }
      },
      {
        "name": {
          "ja": "エネルギーの引き分け"
        },
        "cost": [
          "fighting"
        ],
        "damage": "",
        "text": {
          "ja": "デッキを検索して、基本的なエネルギーカードを調べ、sudowoodoに添付してください。その後、デッキをシャッフルします。"
        }
      }
    ],
    "retreat_cost": 2
  },
  {
    "id": "asia-e3-059",
    "set_id": "asia-e3",
    "number": "059",
    "category": "pokemon",
    "name": {
      "ja": "幼虫"
    },
    "pokemon": [
      "幼虫"
    ],
    "illustrator": null,
    "rarity": "common",
    "regulation_mark": null,
    "variants": [
      {
        "id": "normal",
        "images": {
          "ja": ""
        }
      },
      {
        "id": "stamped",
        "images": {
          "ja": ""
        }
      }
    ],
    "hp": 40,
    "types": [
      "fighting"
    ],
    "stage": "basic",
    "attacks": [
      {
        "name": {
          "ja": "マウンテンイーター"
        },
        "cost": [
          "normal"
        ],
        "damage": "",
        "text": {
          "ja": "あなたの対戦相手は彼または彼女のデッキからトップカードを捨てます。次に、Larvitarからダメージカウンターを削除します。"
        }
      },
      {
        "name": {
          "ja": "上昇する突進"
        },
        "cost": [
          "fighting"
        ],
        "damage": "",
        "text": {
          "ja": "コインをひっくり返します。頭の場合、この攻撃は10ダメージに加えて10ダメージを与えます。"
        }
      }
    ],
    "retreat_cost": 1
  },
  {
    "id": "asia-e3-060",
    "set_id": "asia-e3",
    "number": "060",
    "category": "pokemon",
    "name": {
      "ja": "Pupitar"
    },
    "pokemon": [
      "Pupitar"
    ],
    "illustrator": null,
    "rarity": "common",
    "regulation_mark": null,
    "variants": [
      {
        "id": "normal",
        "images": {
          "ja": ""
        }
      },
      {
        "id": "stamped",
        "images": {
          "ja": ""
        }
      }
    ],
    "hp": 80,
    "types": [
      "fighting"
    ],
    "stage": "stage1",
    "attacks": [
      {
        "name": {
          "ja": "スラッシュ"
        },
        "cost": [
          "normal",
          "normal",
          "normal"
        ],
        "damage": "",
        "text": {
          "ja": "コインをひっくり返します。頭の場合、この攻撃は30ダメージに加えて10ダメージを与えます。尾の場合、Pupitarはそれ自体に10ダメージを与えます。"
        }
      }
    ],
    "retreat_cost": 1
  },
  {
    "id": "asia-e3-061",
    "set_id": "asia-e3",
    "number": "061",
    "category": "pokemon",
    "name": {
      "ja": "ドドゥオ"
    },
    "pokemon": [
      "ドドゥオ"
    ],
    "illustrator": null,
    "rarity": "common",
    "regulation_mark": null,
    "variants": [
      {
        "id": "normal",
        "images": {
          "ja": ""
        }
      },
      {
        "id": "stamped",
        "images": {
          "ja": ""
        }
      }
    ],
    "hp": 40,
    "types": [
      "normal"
    ],
    "stage": "basic",
    "attacks": [
      {
        "name": {
          "ja": "スーパースピード"
        },
        "cost": [
          "normal"
        ],
        "damage": "",
        "text": {
          "ja": "コインをひっくり返します。ヘッドの場合、対戦相手の次のターン中に、ドドゥオに行われた損害を含む攻撃のすべての影響を防ぎます。"
        }
      },
      {
        "name": {
          "ja": "リアキック"
        },
        "cost": [
          "normal",
          "normal"
        ],
        "damage": "20",
        "text": {}
      }
    ],
    "retreat_cost": 1
  },
  {
    "id": "asia-e3-062",
    "set_id": "asia-e3",
    "number": "062",
    "category": "pokemon",
    "name": {
      "ja": "ドドリオ"
    },
    "pokemon": [
      "ドドリオ"
    ],
    "illustrator": null,
    "rarity": "common",
    "regulation_mark": null,
    "variants": [
      {
        "id": "normal",
        "images": {
          "ja": ""
        }
      },
      {
        "id": "stamped",
        "images": {
          "ja": ""
        }
      }
    ],
    "hp": 70,
    "types": [
      "normal"
    ],
    "stage": "stage1",
    "attacks": [
      {
        "name": {
          "ja": "トライ攻撃"
        },
        "cost": [
          "normal"
        ],
        "damage": "",
        "text": {
          "ja": "3コインをフリップします。この攻撃は、ヘッド数の10倍のダメージを与えます。"
        }
      },
      {
        "name": {
          "ja": "ペック攻撃"
        },
        "cost": [
          "normal",
          "normal"
        ],
        "damage": "",
        "text": {
          "ja": "2つのコインをフリップします。それらの1つがヘッドである場合、この攻撃は20のダメージを与えます。両方がヘッドである場合、この攻撃は50のダメージを与えます。両方が尾である場合、防御するポケモンは今混乱しています。"
        }
      }
    ],
    "retreat_cost": 1
  },
  {
    "id": "asia-e3-063",
    "set_id": "asia-e3",
    "number": "063",
    "category": "pokemon",
    "name": {
      "ja": "リキトゥン"
    },
    "pokemon": [
      "リキトゥン"
    ],
    "illustrator": null,
    "rarity": "common",
    "regulation_mark": null,
    "variants": [
      {
        "id": "normal",
        "images": {
          "ja": ""
        }
      },
      {
        "id": "stamped",
        "images": {
          "ja": ""
        }
      }
    ],
    "hp": 80,
    "types": [
      "normal"
    ],
    "stage": "basic",
    "attacks": [
      {
        "name": {
          "ja": "長い舌"
        },
        "cost": [
          "normal",
          "normal"
        ],
        "damage": "",
        "text": {
          "ja": "プレイ中の対戦相手のポケモンを1つ選択します。この攻撃は、そのポケモンに10ダメージを与えます。衰弱と抵抗を適用しないでください。"
        }
      },
      {
        "name": {
          "ja": "ボディスラム"
        },
        "cost": [
          "normal",
          "normal",
          "normal"
        ],
        "damage": "20",
        "text": {
          "ja": "コインをひっくり返します。頭の場合、防御ポケモンは麻痺しています。"
        }
      }
    ],
    "retreat_cost": 2
  },
  {
    "id": "asia-e3-064",
    "set_id": "asia-e3",
    "number": "064",
    "category": "pokemon",
    "name": {
      "ja": "カンガスハン"
    },
    "pokemon": [
      "カンガスハン"
    ],
    "illustrator": null,
    "rarity": "common",
    "regulation_mark": null,
    "variants": [
      {
        "id": "normal",
        "images": {
          "ja": ""
        }
      },
      {
        "id": "stamped",
        "images": {
          "ja": ""
        }
      }
    ],
    "hp": 70,
    "types": [
      "normal"
    ],
    "stage": "basic",
    "attacks": [
      {
        "name": {
          "ja": "赤ちゃんの外出"
        },
        "cost": [
          "normal",
          "normal"
        ],
        "damage": "",
        "text": {
          "ja": "デッキのトップ3のカードを見てから、それらのカードの1枚を選択して、手に入れます。その後、残りをデッキにシャッフルします。"
        }
      },
      {
        "name": {
          "ja": "メガパンチ"
        },
        "cost": [
          "normal",
          "normal",
          "normal"
        ],
        "damage": "30",
        "text": {}
      }
    ],
    "retreat_cost": 2
  },
  {
    "id": "asia-e3-065",
    "set_id": "asia-e3",
    "number": "065",
    "category": "pokemon",
    "name": {
      "ja": "セントレット"
    },
    "pokemon": [
      "セントレット"
    ],
    "illustrator": null,
    "rarity": "common",
    "regulation_mark": null,
    "variants": [
      {
        "id": "normal",
        "images": {
          "ja": ""
        }
      },
      {
        "id": "stamped",
        "images": {
          "ja": ""
        }
      }
    ],
    "hp": 50,
    "types": [
      "normal"
    ],
    "stage": "basic",
    "attacks": [
      {
        "name": {
          "ja": "スパイ"
        },
        "cost": [
          "normal"
        ],
        "damage": "",
        "text": {
          "ja": "対戦相手のデッキのトップ3カードを見てください。それらを同じ順序で戻します。"
        }
      },
      {
        "name": {
          "ja": "二重スクラッチ"
        },
        "cost": [
          "normal"
        ],
        "damage": "",
        "text": {
          "ja": "2つのコインをフリップします。この攻撃は、ヘッド数の10倍のダメージを与えます。"
        }
      }
    ],
    "retreat_cost": 1
  },
  {
    "id": "asia-e3-066",
    "set_id": "asia-e3",
    "number": "066",
    "category": "pokemon",
    "name": {
      "ja": "Furret"
    },
    "pokemon": [
      "Furret"
    ],
    "illustrator": null,
    "rarity": "common",
    "regulation_mark": null,
    "variants": [
      {
        "id": "normal",
        "images": {
          "ja": ""
        }
      }
    ],
    "hp": 70,
    "types": [
      "normal"
    ],
    "stage": "stage1",
    "attacks": [
      {
        "name": {
          "ja": "スピニング攻撃"
        },
        "cost": [
          "normal",
          "normal"
        ],
        "damage": "30",
        "text": {}
      }
    ],
    "retreat_cost": 1
  },
  {
    "id": "asia-e3-067",
    "set_id": "asia-e3",
    "number": "067",
    "category": "pokemon",
    "name": {
      "ja": "aipom"
    },
    "pokemon": [
      "aipom"
    ],
    "illustrator": null,
    "rarity": "common",
    "regulation_mark": null,
    "variants": [
      {
        "id": "normal",
        "images": {
          "ja": ""
        }
      },
      {
        "id": "stamped",
        "images": {
          "ja": ""
        }
      }
    ],
    "hp": 50,
    "types": [
      "normal"
    ],
    "stage": "basic",
    "attacks": [
      {
        "name": {
          "ja": "ストレッチテール"
        },
        "cost": [
          "normal"
        ],
        "damage": "",
        "text": {
          "ja": "コインをひっくり返します。頭の場合は、対戦相手のベンチポケモンの1つを選択すると、この攻撃は10ダメージを与えます。 （ベンチポケモンに衰弱と抵抗を適用しないでください。）"
        }
      },
      {
        "name": {
          "ja": "Skedaddle"
        },
        "cost": [
          "normal",
          "normal"
        ],
        "damage": "20",
        "text": {
          "ja": "Aipomとすべての基本的なエネルギーカードをあなたの手に返します。ベンチ付きポケモンがない場合、この攻撃は何もしません。"
        }
      }
    ],
    "retreat_cost": 1
  },
  {
    "id": "asia-e3-068",
    "set_id": "asia-e3",
    "number": "068",
    "category": "pokemon",
    "name": {
      "ja": "ミルタンク"
    },
    "pokemon": [
      "ミルタンク"
    ],
    "illustrator": null,
    "rarity": "common",
    "regulation_mark": null,
    "variants": [
      {
        "id": "normal",
        "images": {
          "ja": ""
        }
      },
      {
        "id": "stamped",
        "images": {
          "ja": ""
        }
      }
    ],
    "hp": 60,
    "types": [
      "normal"
    ],
    "stage": "basic",
    "attacks": [
      {
        "name": {
          "ja": "取り組む"
        },
        "cost": [
          "normal",
          "normal"
        ],
        "damage": "20",
        "text": {}
      },
      {
        "name": {
          "ja": "連続的なタンブル"
        },
        "cost": [
          "normal",
          "normal"
        ],
        "damage": "",
        "text": {
          "ja": "尾がなくなるまでコインをひっくり返します。この攻撃は、ヘッド数の20倍のダメージを与えます。"
        }
      }
    ],
    "retreat_cost": 1
  },
  {
    "id": "asia-e3-069",
    "set_id": "asia-e3",
    "number": "069",
    "category": "pokemon",
    "name": {
      "ja": "スニーエル"
    },
    "pokemon": [
      "スニーエル"
    ],
    "illustrator": null,
    "rarity": "common",
    "regulation_mark": null,
    "variants": [
      {
        "id": "normal",
        "images": {
          "ja": ""
        }
      },
      {
        "id": "stamped",
        "images": {
          "ja": ""
        }
      }
    ],
    "hp": 60,
    "types": [
      "dark"
    ],
    "stage": "stage1",
    "attacks": [
      {
        "name": {
          "ja": "ロブ"
        },
        "cost": [
          "dark"
        ],
        "damage": "",
        "text": {
          "ja": "相手の手を見てください。そこにすべてのテクニカルマシンとポケモンのツールカードを選択し、それらを彼または彼女のデッキに入れます。あなたの対戦相手はその後デッキをシャッフルします。"
        }
      },
      {
        "name": {
          "ja": "爪"
        },
        "cost": [
          "normal",
          "normal"
        ],
        "damage": "30",
        "text": {
          "ja": "コインをひっくり返します。尾の場合、この攻撃は何もしません。"
        }
      }
    ],
    "retreat_cost": 1
  },
  {
    "id": "asia-e3-070",
    "set_id": "asia-e3",
    "number": "070",
    "category": "pokemon",
    "name": {
      "ja": "タイラニター"
    },
    "pokemon": [
      "タイラニター"
    ],
    "illustrator": null,
    "rarity": "rare",
    "regulation_mark": null,
    "variants": [
      {
        "id": "normal",
        "images": {
          "ja": ""
        }
      }
    ],
    "hp": 120,
    "types": [
      "dark"
    ],
    "stage": "stage2",
    "attacks": [
      {
        "name": {
          "ja": "破壊的なro音"
        },
        "cost": [
          "dark"
        ],
        "damage": "",
        "text": {
          "ja": "コインをひっくり返します。頭の場合は、1匹の敵のポケモンに取り付けられた1枚のエネルギーカードを捨てます。"
        }
      },
      {
        "name": {
          "ja": "テールスラップ"
        },
        "cost": [
          "dark",
          "normal",
          "normal"
        ],
        "damage": "30",
        "text": {}
      },
      {
        "name": {
          "ja": "GigaCrush"
        },
        "cost": [
          "dark",
          "dark",
          "normal",
          "normal",
          "normal"
        ],
        "damage": "60",
        "text": {
          "ja": "各プレイヤーは、上位3枚のカードをデッキから破棄します。"
        }
      }
    ],
    "retreat_cost": 3
  },
  {
    "id": "asia-e3-071",
    "set_id": "asia-e3",
    "number": "071",
    "category": "pokemon",
    "name": {
      "ja": "タイラニター"
    },
    "pokemon": [
      "タイラニター"
    ],
    "illustrator": null,
    "rarity": "holo_rare",
    "regulation_mark": null,
    "variants": [
      {
        "id": "holo",
        "images": {
          "ja": ""
        }
      }
    ],
    "hp": 120,
    "types": [
      "dark"
    ],
    "stage": "stage2",
    "attacks": [
      {
        "name": {
          "ja": "破壊的なro音"
        },
        "cost": [
          "dark"
        ],
        "damage": "",
        "text": {
          "ja": "コインをひっくり返します。頭の場合は、1匹の敵のポケモンに取り付けられた1枚のエネルギーカードを捨てます。"
        }
      },
      {
        "name": {
          "ja": "テールスラップ"
        },
        "cost": [
          "dark",
          "normal",
          "normal"
        ],
        "damage": "30",
        "text": {}
      },
      {
        "name": {
          "ja": "GigaCrush"
        },
        "cost": [
          "dark",
          "dark",
          "normal",
          "normal",
          "normal"
        ],
        "damage": "60",
        "text": {
          "ja": "各プレイヤーは、上位3枚のカードをデッキから破棄します。"
        }
      }
    ],
    "retreat_cost": 3
  },
  {
    "id": "asia-e3-072",
    "set_id": "asia-e3",
    "number": "072",
    "category": "pokemon",
    "name": {
      "ja": "Steelix"
    },
    "pokemon": [
      "Steelix"
    ],
    "illustrator": null,
    "rarity": "rare",
    "regulation_mark": null,
    "variants": [
      {
        "id": "normal",
        "images": {
          "ja": ""
        }
      }
    ],
    "hp": 100,
    "types": [
      "metal"
    ],
    "stage": "stage1",
    "attacks": [
      {
        "name": {
          "ja": "地球の裂け目"
        },
        "cost": [
          "normal",
          "normal"
        ],
        "damage": "10",
        "text": {
          "ja": "この攻撃は、相手のベンチポケモンのそれぞれに10ダメージを与えます。 （ベンチポケモンに脱力や抵抗を適用しないでください。）次に、コインをひっくり返します。テールの場合、この攻撃は次のターン中に使用できません。"
        }
      },
      {
        "name": {
          "ja": "アイアンスマッシュ"
        },
        "cost": [
          "metal",
          "metal",
          "normal",
          "normal"
        ],
        "damage": "",
        "text": {
          "ja": "2つのコインをフリップします。両方がヘッドである場合、この攻撃は50のダメージと20のダメージをさらに20回かけます。両方が尾の場合、この攻撃は何もしません。 1がヘッドで、1がテールの場合、この攻撃は50ダメージを与えます。"
        }
      }
    ],
    "retreat_cost": 4
  },
  {
    "id": "asia-e3-073",
    "set_id": "asia-e3",
    "number": "073",
    "category": "pokemon",
    "name": {
      "ja": "Steelix"
    },
    "pokemon": [
      "Steelix"
    ],
    "illustrator": null,
    "rarity": "holo_rare",
    "regulation_mark": null,
    "variants": [
      {
        "id": "holo",
        "images": {
          "ja": ""
        }
      },
      {
        "id": "stamped",
        "images": {
          "ja": ""
        }
      }
    ],
    "hp": 100,
    "types": [
      "metal"
    ],
    "stage": "stage1",
    "attacks": [
      {
        "name": {
          "ja": "地球の裂け目"
        },
        "cost": [
          "normal",
          "normal"
        ],
        "damage": "10",
        "text": {
          "ja": "この攻撃は、相手のベンチポケモンのそれぞれに10ダメージを与えます。 （ベンチポケモンに脱力や抵抗を適用しないでください。）次に、コインをひっくり返します。テールの場合、この攻撃は次のターン中に使用できません。"
        }
      },
      {
        "name": {
          "ja": "アイアンスマッシュ"
        },
        "cost": [
          "metal",
          "metal",
          "normal",
          "normal"
        ],
        "damage": "",
        "text": {
          "ja": "2つのコインをフリップします。両方がヘッドである場合、この攻撃は50のダメージと20のダメージをさらに20回かけます。両方が尾の場合、この攻撃は何もしません。 1がヘッドで、1がテールの場合、この攻撃は50ダメージを与えます。"
        }
      }
    ],
    "retreat_cost": 4
  },
  {
    "id": "asia-e3-074",
    "set_id": "asia-e3",
    "number": "074",
    "category": "pokemon",
    "name": {
      "ja": "Scizor"
    },
    "pokemon": [
      "Scizor"
    ],
    "illustrator": null,
    "rarity": "rare",
    "regulation_mark": null,
    "variants": [
      {
        "id": "normal",
        "images": {
          "ja": ""
        }
      }
    ],
    "hp": 80,
    "types": [
      "metal"
    ],
    "stage": "stage1",
    "attacks": [
      {
        "name": {
          "ja": "スナッチ"
        },
        "cost": [
          "metal",
          "normal"
        ],
        "damage": "20",
        "text": {
          "ja": "ダメージを与える前に、ダメージカウンターなしで対戦相手のベンチ付きポケモンを1つ選択し、防御ポケモンをそれに切り替えることができます。"
        }
      },
      {
        "name": {
          "ja": "重金属"
        },
        "cost": [
          "normal",
          "normal",
          "normal"
        ],
        "damage": "",
        "text": {
          "ja": "Scizorに取り付けられた金属エネルギーの量に等しい多数のコインをひっくり返します。この攻撃は、30のダメージに加えて、ヘッドごとに20のダメージを与えます。"
        }
      }
    ],
    "retreat_cost": 2
  },
  {
    "id": "asia-e3-075",
    "set_id": "asia-e3",
    "number": "075",
    "category": "pokemon",
    "name": {
      "ja": "Scizor"
    },
    "pokemon": [
      "Scizor"
    ],
    "illustrator": null,
    "rarity": "holo_rare",
    "regulation_mark": null,
    "variants": [
      {
        "id": "normal",
        "images": {
          "ja": ""
        }
      }
    ],
    "hp": 80,
    "types": [
      "metal"
    ],
    "stage": "stage1",
    "attacks": [
      {
        "name": {
          "ja": "スナッチ"
        },
        "cost": [
          "metal",
          "normal"
        ],
        "damage": "20",
        "text": {
          "ja": "ダメージを与える前に、ダメージカウンターなしで対戦相手のベンチ付きポケモンを1つ選択し、防御ポケモンをそれに切り替えることができます。"
        }
      },
      {
        "name": {
          "ja": "重金属"
        },
        "cost": [
          "normal",
          "normal",
          "normal"
        ],
        "damage": "",
        "text": {
          "ja": "Scizorに取り付けられた金属エネルギーの量に等しい多数のコインをひっくり返します。この攻撃は、30のダメージに加えて、ヘッドごとに20のダメージを与えます。"
        }
      }
    ],
    "retreat_cost": 2
  },
  {
    "id": "asia-e3-076",
    "set_id": "asia-e3",
    "number": "076",
    "category": "trainer",
    "name": {
      "ja": "エネルギースイッチ"
    },
    "pokemon": [],
    "illustrator": null,
    "rarity": "uncommon",
    "regulation_mark": null,
    "variants": [
      {
        "id": "normal",
        "images": {
          "ja": ""
        }
      }
    ]
  },
  {
    "id": "asia-e3-077",
    "set_id": "asia-e3",
    "number": "077",
    "category": "trainer",
    "name": {
      "ja": "旅行セールスマン"
    },
    "pokemon": [],
    "illustrator": null,
    "rarity": "uncommon",
    "regulation_mark": null,
    "variants": [
      {
        "id": "normal",
        "images": {
          "ja": ""
        }
      },
      {
        "id": "stamped",
        "images": {
          "ja": ""
        }
      }
    ]
  },
  {
    "id": "asia-e3-078",
    "set_id": "asia-e3",
    "number": "078",
    "category": "trainer",
    "name": {
      "ja": "ジャグラー"
    },
    "pokemon": [],
    "illustrator": null,
    "rarity": "uncommon",
    "regulation_mark": null,
    "variants": [
      {
        "id": "normal",
        "images": {
          "ja": ""
        }
      },
      {
        "id": "stamped",
        "images": {
          "ja": ""
        }
      }
    ]
  },
  {
    "id": "asia-e3-079",
    "set_id": "asia-e3",
    "number": "079",
    "category": "trainer",
    "name": {
      "ja": "森林保護者"
    },
    "pokemon": [],
    "illustrator": null,
    "rarity": "uncommon",
    "regulation_mark": null,
    "variants": [
      {
        "id": "normal",
        "images": {
          "ja": ""
        }
      },
      {
        "id": "stamped",
        "images": {
          "ja": ""
        }
      }
    ]
  },
  {
    "id": "asia-e3-080",
    "set_id": "asia-e3",
    "number": "080",
    "category": "trainer",
    "name": {
      "ja": "メモリベリー"
    },
    "pokemon": [],
    "illustrator": null,
    "rarity": "uncommon",
    "regulation_mark": null,
    "variants": [
      {
        "id": "normal",
        "images": {
          "ja": ""
        }
      },
      {
        "id": "stamped",
        "images": {
          "ja": ""
        }
      }
    ]
  },
  {
    "id": "asia-e3-081",
    "set_id": "asia-e3",
    "number": "081",
    "category": "trainer",
    "name": {
      "ja": "癒しベリー"
    },
    "pokemon": [],
    "illustrator": null,
    "rarity": "uncommon",
    "regulation_mark": null,
    "variants": [
      {
        "id": "normal",
        "images": {
          "ja": ""
        }
      },
      {
        "id": "stamped",
        "images": {
          "ja": ""
        }
      }
    ]
  },
  {
    "id": "asia-e3-082",
    "set_id": "asia-e3",
    "number": "082",
    "category": "trainer",
    "name": {
      "ja": "タイムシャード"
    },
    "pokemon": [],
    "illustrator": null,
    "rarity": "uncommon",
    "regulation_mark": null,
    "variants": [
      {
        "id": "normal",
        "images": {
          "ja": ""
        }
      },
      {
        "id": "stamped",
        "images": {
          "ja": ""
        }
      }
    ]
  },
  {
    "id": "asia-e3-083",
    "set_id": "asia-e3",
    "number": "083",
    "category": "trainer",
    "name": {
      "ja": "海底遺跡"
    },
    "pokemon": [],
    "illustrator": null,
    "rarity": "uncommon",
    "regulation_mark": null,
    "variants": [
      {
        "id": "normal",
        "images": {
          "ja": ""
        }
      },
      {
        "id": "stamped",
        "images": {
          "ja": ""
        }
      }
    ]
  },
  {
    "id": "asia-e3-084",
    "set_id": "asia-e3",
    "number": "084",
    "category": "trainer",
    "name": {
      "ja": "アプリコーンの森"
    },
    "pokemon": [],
    "illustrator": null,
    "rarity": "uncommon",
    "regulation_mark": null,
    "variants": [
      {
        "id": "normal",
        "images": {
          "ja": ""
        }
      },
      {
        "id": "stamped",
        "images": {
          "ja": ""
        }
      }
    ]
  },
  {
    "id": "asia-e3-085",
    "set_id": "asia-e3",
    "number": "085",
    "category": "trainer",
    "name": {
      "ja": "クリスタルエネルギー"
    },
    "pokemon": [],
    "illustrator": null,
    "rarity": "uncommon",
    "regulation_mark": null,
    "variants": [
      {
        "id": "normal",
        "images": {
          "ja": ""
        }
      },
      {
        "id": "stamped",
        "images": {
          "ja": ""
        }
      }
    ]
  },
  {
    "id": "asia-e3-086",
    "set_id": "asia-e3",
    "number": "086",
    "category": "trainer",
    "name": {
      "ja": "エネルギーを高めます"
    },
    "pokemon": [],
    "illustrator": null,
    "rarity": "uncommon",
    "regulation_mark": null,
    "variants": [
      {
        "id": "normal",
        "images": {
          "ja": ""
        }
      }
    ]
  },
  {
    "id": "asia-e3-087",
    "set_id": "asia-e3",
    "number": "087",
    "category": "trainer",
    "name": {
      "ja": "ワープエネルギー"
    },
    "pokemon": [],
    "illustrator": null,
    "rarity": "uncommon",
    "regulation_mark": null,
    "variants": [
      {
        "id": "normal",
        "images": {
          "ja": ""
        }
      },
      {
        "id": "stamped",
        "images": {
          "ja": ""
        }
      }
    ]
  },
  {
    "id": "asia-e3-088",
    "set_id": "asia-e3",
    "number": "088",
    "category": "pokemon",
    "name": {
      "ja": "ニドキング"
    },
    "pokemon": [
      "ニドキング"
    ],
    "illustrator": null,
    "rarity": "secret_rare",
    "regulation_mark": null,
    "variants": [
      {
        "id": "normal",
        "images": {
          "ja": ""
        }
      }
    ],
    "hp": 100,
    "types": [
      "normal"
    ],
    "stage": "stage2",
    "attacks": [
      {
        "name": {
          "ja": "ポイズンホーン"
        },
        "cost": [
          "grass",
          "grass",
          "normal"
        ],
        "damage": "20",
        "text": {
          "ja": "防御ポケモンは現在中毒になっています。"
        }
      },
      {
        "name": {
          "ja": "ローリングサンダー"
        },
        "cost": [
          "lightning",
          "lightning",
          "fighting",
          "fighting"
        ],
        "damage": "50",
        "text": {
          "ja": "コインをひっくり返します。頭の場合、この攻撃は相手のベンチポケモンのそれぞれに10ダメージを与えます。尾の場合、この攻撃はベンチポケモンのそれぞれに10ダメージを与えます。 （ベンチポケモンに衰弱や抵抗を適用しないでください。）"
        }
      }
    ],
    "retreat_cost": 3
  },
  {
    "id": "asia-e3-089",
    "set_id": "asia-e3",
    "number": "089",
    "category": "pokemon",
    "name": {
      "ja": "キングドラ"
    },
    "pokemon": [
      "キングドラ"
    ],
    "illustrator": null,
    "rarity": "secret_rare",
    "regulation_mark": null,
    "variants": [
      {
        "id": "normal",
        "images": {
          "ja": ""
        }
      }
    ],
    "hp": 110,
    "types": [
      "normal"
    ],
    "stage": "stage2",
    "attacks": [
      {
        "name": {
          "ja": "Aquabomb"
        },
        "cost": [
          "water",
          "water",
          "lightning"
        ],
        "damage": "40",
        "text": {
          "ja": "Kingdraはそれ自体に10ダメージを与えます。 （Kingdraがこの攻撃で損害を与える場合、衰弱や抵抗を適用しないでください。）"
        }
      },
      {
        "name": {
          "ja": "二重火傷"
        },
        "cost": [
          "psychic",
          "psychic",
          "lightning",
          "normal"
        ],
        "damage": "60",
        "text": {
          "ja": "2つのコインをフリップします。各テールについて、Kingdraに取り付けられた1つのエネルギーカードを捨てます。"
        }
      }
    ],
    "retreat_cost": 3
  },
  {
    "id": "asia-e3-090",
    "set_id": "asia-e3",
    "number": "090",
    "category": "pokemon",
    "name": {
      "ja": "ルギア"
    },
    "pokemon": [
      "ルギア"
    ],
    "illustrator": null,
    "rarity": "secret_rare",
    "regulation_mark": null,
    "variants": [
      {
        "id": "normal",
        "images": {
          "ja": ""
        }
      }
    ],
    "hp": 80,
    "types": [
      "normal"
    ],
    "stage": "basic",
    "attacks": [
      {
        "name": {
          "ja": "サイキック"
        },
        "cost": [
          "psychic",
          "fire"
        ],
        "damage": "",
        "text": {
          "ja": "この攻撃は、防御ポケモンに添付されているエネルギーカードの数の10倍のダメージを与えます。"
        }
      },
      {
        "name": {
          "ja": "蒸気爆発"
        },
        "cost": [
          "water",
          "water",
          "fire",
          "normal"
        ],
        "damage": "50",
        "text": {
          "ja": "Lugiaに取り付けられたエネルギーカードを廃棄します。"
        }
      }
    ],
    "retreat_cost": 3
  }
]
